{
  "active_lock_reason": null,
  "assignee": {
    "avatar_url": "https://avatars3.githubusercontent.com/u/11657829?v=4",
    "events_url": "https://api.github.com/users/ravisantoshgudimetla/events{/privacy}",
    "followers_url": "https://api.github.com/users/ravisantoshgudimetla/followers",
    "following_url": "https://api.github.com/users/ravisantoshgudimetla/following{/other_user}",
    "gists_url": "https://api.github.com/users/ravisantoshgudimetla/gists{/gist_id}",
    "gravatar_id": "",
    "html_url": "https://github.com/ravisantoshgudimetla",
    "id": 11657829,
    "login": "ravisantoshgudimetla",
    "node_id": "MDQ6VXNlcjExNjU3ODI5",
    "organizations_url": "https://api.github.com/users/ravisantoshgudimetla/orgs",
    "received_events_url": "https://api.github.com/users/ravisantoshgudimetla/received_events",
    "repos_url": "https://api.github.com/users/ravisantoshgudimetla/repos",
    "site_admin": false,
    "starred_url": "https://api.github.com/users/ravisantoshgudimetla/starred{/owner}{/repo}",
    "subscriptions_url": "https://api.github.com/users/ravisantoshgudimetla/subscriptions",
    "type": "User",
    "url": "https://api.github.com/users/ravisantoshgudimetla"
  },
  "assignees": [
    {
      "avatar_url": "https://avatars3.githubusercontent.com/u/11657829?v=4",
      "events_url": "https://api.github.com/users/ravisantoshgudimetla/events{/privacy}",
      "followers_url": "https://api.github.com/users/ravisantoshgudimetla/followers",
      "following_url": "https://api.github.com/users/ravisantoshgudimetla/following{/other_user}",
      "gists_url": "https://api.github.com/users/ravisantoshgudimetla/gists{/gist_id}",
      "gravatar_id": "",
      "html_url": "https://github.com/ravisantoshgudimetla",
      "id": 11657829,
      "login": "ravisantoshgudimetla",
      "node_id": "MDQ6VXNlcjExNjU3ODI5",
      "organizations_url": "https://api.github.com/users/ravisantoshgudimetla/orgs",
      "received_events_url": "https://api.github.com/users/ravisantoshgudimetla/received_events",
      "repos_url": "https://api.github.com/users/ravisantoshgudimetla/repos",
      "site_admin": false,
      "starred_url": "https://api.github.com/users/ravisantoshgudimetla/starred{/owner}{/repo}",
      "subscriptions_url": "https://api.github.com/users/ravisantoshgudimetla/subscriptions",
      "type": "User",
      "url": "https://api.github.com/users/ravisantoshgudimetla"
    }
  ],
  "author_association": "CONTRIBUTOR",
  "body": "<!-- Thanks for filing an issue! Before hitting the button, please answer these questions.-->\r\n\r\nAs a follow-up on the discussion that we had on #43171 and sig-scheduling meeting, I wish to consolidate the points that were raised there wrt taints logic sprawl in kubectl.\r\n\r\n- Some functions like reorganizeTaints in taints.go in pkg/kubectl/cmd/ need to moved to another location(either api/helpers.go or new TaintController pkg) - @gmarek, @timothysc \r\n- Refactor the testing suite to reflect the new changes.\r\n\r\nThose are specific to the kubectl. \r\n\r\n/cc @timothysc @gmarek @aveshagarwal @k82cn @adohe @jayunit100\r\n\r\nPlease add other files if you happen(ned) to work or if you know. ",
  "closed_at": "2017-07-22T05:23:24Z",
  "closed_by": {
    "avatar_url": "https://avatars0.githubusercontent.com/u/13653959?v=4",
    "events_url": "https://api.github.com/users/k8s-github-robot/events{/privacy}",
    "followers_url": "https://api.github.com/users/k8s-github-robot/followers",
    "following_url": "https://api.github.com/users/k8s-github-robot/following{/other_user}",
    "gists_url": "https://api.github.com/users/k8s-github-robot/gists{/gist_id}",
    "gravatar_id": "",
    "html_url": "https://github.com/k8s-github-robot",
    "id": 13653959,
    "login": "k8s-github-robot",
    "node_id": "MDQ6VXNlcjEzNjUzOTU5",
    "organizations_url": "https://api.github.com/users/k8s-github-robot/orgs",
    "received_events_url": "https://api.github.com/users/k8s-github-robot/received_events",
    "repos_url": "https://api.github.com/users/k8s-github-robot/repos",
    "site_admin": false,
    "starred_url": "https://api.github.com/users/k8s-github-robot/starred{/owner}{/repo}",
    "subscriptions_url": "https://api.github.com/users/k8s-github-robot/subscriptions",
    "type": "User",
    "url": "https://api.github.com/users/k8s-github-robot"
  },
  "comments": 10,
  "comments_url": "https://api.github.com/repos/kubernetes/kubernetes/issues/45060/comments",
  "created_at": "2017-04-28T01:32:32Z",
  "events_url": "https://api.github.com/repos/kubernetes/kubernetes/issues/45060/events",
  "html_url": "https://github.com/kubernetes/kubernetes/issues/45060",
  "id": 224956184,
  "labels": [
    {
      "color": "c7def8",
      "default": false,
      "description": "Categorizes issue or PR as related to cleaning up code, process, or technical debt.",
      "id": 122775691,
      "name": "kind/cleanup",
      "node_id": "MDU6TGFiZWwxMjI3NzU2OTE=",
      "url": "https://api.github.com/repos/kubernetes/kubernetes/labels/kind/cleanup"
    },
    {
      "color": "d2b48c",
      "default": false,
      "description": "Categorizes an issue or PR as relevant to SIG API Machinery.",
      "id": 173493835,
      "name": "sig/api-machinery",
      "node_id": "MDU6TGFiZWwxNzM0OTM4MzU=",
      "url": "https://api.github.com/repos/kubernetes/kubernetes/labels/sig/api-machinery"
    },
    {
      "color": "d2b48c",
      "default": false,
      "description": "Categorizes an issue or PR as relevant to SIG Scheduling.",
      "id": 125550211,
      "name": "sig/scheduling",
      "node_id": "MDU6TGFiZWwxMjU1NTAyMTE=",
      "url": "https://api.github.com/repos/kubernetes/kubernetes/labels/sig/scheduling"
    }
  ],
  "labels_url": "https://api.github.com/repos/kubernetes/kubernetes/issues/45060/labels{/name}",
  "locked": false,
  "milestone": null,
  "node_id": "MDU6SXNzdWUyMjQ5NTYxODQ=",
  "number": 45060,
  "performed_via_github_app": null,
  "repository_url": "https://api.github.com/repos/kubernetes/kubernetes",
  "state": "closed",
  "title": "Refactoring taints logic to reduce sprawl across components.",
  "updated_at": "2017-07-22T05:23:24Z",
  "url": "https://api.github.com/repos/kubernetes/kubernetes/issues/45060",
  "user": {
    "avatar_url": "https://avatars3.githubusercontent.com/u/11657829?v=4",
    "events_url": "https://api.github.com/users/ravisantoshgudimetla/events{/privacy}",
    "followers_url": "https://api.github.com/users/ravisantoshgudimetla/followers",
    "following_url": "https://api.github.com/users/ravisantoshgudimetla/following{/other_user}",
    "gists_url": "https://api.github.com/users/ravisantoshgudimetla/gists{/gist_id}",
    "gravatar_id": "",
    "html_url": "https://github.com/ravisantoshgudimetla",
    "id": 11657829,
    "login": "ravisantoshgudimetla",
    "node_id": "MDQ6VXNlcjExNjU3ODI5",
    "organizations_url": "https://api.github.com/users/ravisantoshgudimetla/orgs",
    "received_events_url": "https://api.github.com/users/ravisantoshgudimetla/received_events",
    "repos_url": "https://api.github.com/users/ravisantoshgudimetla/repos",
    "site_admin": false,
    "starred_url": "https://api.github.com/users/ravisantoshgudimetla/starred{/owner}{/repo}",
    "subscriptions_url": "https://api.github.com/users/ravisantoshgudimetla/subscriptions",
    "type": "User",
    "url": "https://api.github.com/users/ravisantoshgudimetla"
  }
}