{
  "active_lock_reason": null,
  "assignee": {
    "avatar_url": "https://avatars3.githubusercontent.com/u/6233452?v=4",
    "events_url": "https://api.github.com/users/derekwaynecarr/events{/privacy}",
    "followers_url": "https://api.github.com/users/derekwaynecarr/followers",
    "following_url": "https://api.github.com/users/derekwaynecarr/following{/other_user}",
    "gists_url": "https://api.github.com/users/derekwaynecarr/gists{/gist_id}",
    "gravatar_id": "",
    "html_url": "https://github.com/derekwaynecarr",
    "id": 6233452,
    "login": "derekwaynecarr",
    "node_id": "MDQ6VXNlcjYyMzM0NTI=",
    "organizations_url": "https://api.github.com/users/derekwaynecarr/orgs",
    "received_events_url": "https://api.github.com/users/derekwaynecarr/received_events",
    "repos_url": "https://api.github.com/users/derekwaynecarr/repos",
    "site_admin": false,
    "starred_url": "https://api.github.com/users/derekwaynecarr/starred{/owner}{/repo}",
    "subscriptions_url": "https://api.github.com/users/derekwaynecarr/subscriptions",
    "type": "User",
    "url": "https://api.github.com/users/derekwaynecarr"
  },
  "assignees": [
    {
      "avatar_url": "https://avatars3.githubusercontent.com/u/6233452?v=4",
      "events_url": "https://api.github.com/users/derekwaynecarr/events{/privacy}",
      "followers_url": "https://api.github.com/users/derekwaynecarr/followers",
      "following_url": "https://api.github.com/users/derekwaynecarr/following{/other_user}",
      "gists_url": "https://api.github.com/users/derekwaynecarr/gists{/gist_id}",
      "gravatar_id": "",
      "html_url": "https://github.com/derekwaynecarr",
      "id": 6233452,
      "login": "derekwaynecarr",
      "node_id": "MDQ6VXNlcjYyMzM0NTI=",
      "organizations_url": "https://api.github.com/users/derekwaynecarr/orgs",
      "received_events_url": "https://api.github.com/users/derekwaynecarr/received_events",
      "repos_url": "https://api.github.com/users/derekwaynecarr/repos",
      "site_admin": false,
      "starred_url": "https://api.github.com/users/derekwaynecarr/starred{/owner}{/repo}",
      "subscriptions_url": "https://api.github.com/users/derekwaynecarr/subscriptions",
      "type": "User",
      "url": "https://api.github.com/users/derekwaynecarr"
    }
  ],
  "author_association": "CONTRIBUTOR",
  "body": "In my env there is sufficient disk but after run kubernetes all-in-one env(hack/local-up-cluster.sh), the node status is always \"OutOfDisk\"\n\n```\n1. Check node OutOfDisk status\n[root@ip-172-18-9-37 amd64]# ./kubectl describe node/127.0.0.1 | grep -w OutOfDisk\n  OutOfDisk         True    Tue, 05 Jul 2016 01:40:44 -0400     Tue, 05 Jul 2016 01:37:57 -0400     KubeletOutOfDisk        out of disk space\n[root@ip-172-18-9-37 amd64]# df -lh\nFilesystem                                       Size  Used Avail Use% Mounted on\n/dev/xvda2                                        25G   13G   13G  49% /\ndevtmpfs                                         3.9G     0  3.9G   0% /dev\ntmpfs                                            3.7G     0  3.7G   0% /dev/shm\ntmpfs                                            3.7G   17M  3.7G   1% /run\ntmpfs                                            3.7G     0  3.7G   0% /sys/fs/cgroup\n/dev/mapper/docker--vg-openshift--xfs--vol--dir 1014M   33M  982M   4% /mnt/openshift-xfs-vol-dir\ntmpfs                                            757M     0  757M   0% /run/user/0\ntmpfs                                            3.7G   16K  3.7G   1% /data/src/github.com/openshift/origin/openshift.local.volumes/pods/413b5f76-425a-11e6-9b3d-0e3794ecd4b1/volumes/kubernetes.io~secret/registry-token-jm1uv\ntmpfs                                            3.7G   16K  3.7G   1% /data/src/github.com/openshift/origin/openshift.local.volumes/pods/4247b8cf-425a-11e6-9b3d-0e3794ecd4b1/volumes/kubernetes.io~secret/router-token-bfq42\n[root@ip-172-18-9-37 amd64]# docker info\nContainers: 1\n Running: 0\n Paused: 0\n Stopped: 1\nImages: 4\nServer Version: 1.10.3\nStorage Driver: devicemapper\n Pool Name: docker-202:2-117755246-pool\n Pool Blocksize: 65.54 kB\n Base Device Size: 10.74 GB\n Backing Filesystem: xfs\n Data file: /dev/docker-vg/docker-data\n Metadata file: /dev/docker-vg/docker-metadata\n Data Space Used: 1.325 GB\n Data Space Total: 19.32 GB\n Data Space Available: 18 GB\n Metadata Space Used: 1.401 MB\n Metadata Space Total: 1.074 GB\n Metadata Space Available: 1.072 GB\n Udev Sync Supported: true\n Deferred Removal Enabled: true\n Deferred Deletion Enabled: true\n Deferred Deleted Device Count: 0\n Library Version: 1.02.107-RHEL7 (2016-06-09)\nExecution Driver: native-0.2\nLogging Driver: journald\nPlugins: \n Volume: local\n Network: null host bridge\n Authorization: rhel-push-plugin\nKernel Version: 3.10.0-229.7.2.el7.x86_64\nOperating System: Red Hat Enterprise Linux Server 7.2 (Maipo)\nOSType: linux\nArchitecture: x86_64\nNumber of Docker Hooks: 2\nCPUs: 2\nTotal Memory: 7.389 GiB\nName: ip-172-18-9-37.ec2.internal\nID: XWWJ:VSCM:IPAG:I46X:EWGM:FUS4:6STD:BVWQ:XQVL:ZQ5M:76C3:ETXX\nWARNING: bridge-nf-call-ip6tables is disabled\nRegistries: docker.io (secure)\n[root@ip-172-18-9-37 amd64]# curl -k http://localhost:4194/api/v2.1/storage | python -m json.tool\n  % Total    % Received % Xferd  Average Speed   Time    Time     Time  Current\n                                 Dload  Upload   Total   Spent    Left  Speed\n100   515  100   515    0     0   102k      0 --:--:-- --:--:-- --:--:--  125k\n[\n    {\n        \"available\": 13834489856,\n        \"capacity\": 26830942208,\n        \"device\": \"/dev/xvda2\",\n        \"inodes_free\": 25997876,\n        \"labels\": [\n            \"root\"\n        ],\n        \"mountpoint\": \"/\",\n        \"usage\": 12996452352\n    },\n    {\n        \"available\": 1029529600,\n        \"capacity\": 1063256064,\n        \"device\": \"/dev/mapper/docker--vg-openshift--xfs--vol--dir\",\n        \"inodes_free\": 1048572,\n        \"labels\": [],\n        \"mountpoint\": \"/mnt/openshift-xfs-vol-dir\",\n        \"usage\": 33726464\n    },\n    {\n        \"available\": 17998282752,\n        \"capacity\": 19323158528,\n        \"device\": \"docker-202:2-117755246-pool\",\n        \"inodes_free\": 0,\n        \"labels\": [\n            \"docker-images\"\n        ],\n        \"mountpoint\": \"\",\n        \"usage\": 1324875776\n    }\n]\n\n[root@ip-172-18-9-37 amd64]# ./kubectl version\nClient Version: version.Info{Major:\"1\", Minor:\"4+\", GitVersion:\"v1.4.0-alpha.0.1216+cd7a56ba4697ec\", GitCommit:\"cd7a56ba4697ecd49f8331cb6a2664dbfa4517d1\", GitTreeState:\"clean\", BuildDate:\"2016-07-05T01:36:43Z\", GoVersion:\"go1.6.2\", Compiler:\"gc\", Platform:\"linux/amd64\"}\nServer Version: version.Info{Major:\"1\", Minor:\"4+\", GitVersion:\"v1.4.0-alpha.0.1216+cd7a56ba4697ec\", GitCommit:\"cd7a56ba4697ecd49f8331cb6a2664dbfa4517d1\", GitTreeState:\"clean\", BuildDate:\"2016-07-05T01:36:43Z\", GoVersion:\"go1.6.2\", Compiler:\"gc\", Platform:\"linux/amd64\"}\n\n```\n",
  "closed_at": "2016-07-07T00:59:17Z",
  "closed_by": {
    "avatar_url": "https://avatars0.githubusercontent.com/u/13653959?v=4",
    "events_url": "https://api.github.com/users/k8s-github-robot/events{/privacy}",
    "followers_url": "https://api.github.com/users/k8s-github-robot/followers",
    "following_url": "https://api.github.com/users/k8s-github-robot/following{/other_user}",
    "gists_url": "https://api.github.com/users/k8s-github-robot/gists{/gist_id}",
    "gravatar_id": "",
    "html_url": "https://github.com/k8s-github-robot",
    "id": 13653959,
    "login": "k8s-github-robot",
    "node_id": "MDQ6VXNlcjEzNjUzOTU5",
    "organizations_url": "https://api.github.com/users/k8s-github-robot/orgs",
    "received_events_url": "https://api.github.com/users/k8s-github-robot/received_events",
    "repos_url": "https://api.github.com/users/k8s-github-robot/repos",
    "site_admin": false,
    "starred_url": "https://api.github.com/users/k8s-github-robot/starred{/owner}{/repo}",
    "subscriptions_url": "https://api.github.com/users/k8s-github-robot/subscriptions",
    "type": "User",
    "url": "https://api.github.com/users/k8s-github-robot"
  },
  "comments": 6,
  "comments_url": "https://api.github.com/repos/kubernetes/kubernetes/issues/28481/comments",
  "created_at": "2016-07-05T03:20:57Z",
  "events_url": "https://api.github.com/repos/kubernetes/kubernetes/issues/28481/events",
  "html_url": "https://github.com/kubernetes/kubernetes/issues/28481",
  "id": 163765327,
  "labels": [
    {
      "color": "eb6420",
      "default": false,
      "description": "Must be staffed and worked on either currently, or very soon, ideally in time for the next release.",
      "id": 114528223,
      "name": "priority/important-soon",
      "node_id": "MDU6TGFiZWwxMTQ1MjgyMjM=",
      "url": "https://api.github.com/repos/kubernetes/kubernetes/labels/priority/important-soon"
    }
  ],
  "labels_url": "https://api.github.com/repos/kubernetes/kubernetes/issues/28481/labels{/name}",
  "locked": false,
  "milestone": {
    "closed_at": "2019-08-26T17:23:33Z",
    "closed_issues": 1404,
    "created_at": "2016-05-19T18:50:19Z",
    "creator": {
      "avatar_url": "https://avatars1.githubusercontent.com/u/7725777?v=4",
      "events_url": "https://api.github.com/users/bgrant0607/events{/privacy}",
      "followers_url": "https://api.github.com/users/bgrant0607/followers",
      "following_url": "https://api.github.com/users/bgrant0607/following{/other_user}",
      "gists_url": "https://api.github.com/users/bgrant0607/gists{/gist_id}",
      "gravatar_id": "",
      "html_url": "https://github.com/bgrant0607",
      "id": 7725777,
      "login": "bgrant0607",
      "node_id": "MDQ6VXNlcjc3MjU3Nzc=",
      "organizations_url": "https://api.github.com/users/bgrant0607/orgs",
      "received_events_url": "https://api.github.com/users/bgrant0607/received_events",
      "repos_url": "https://api.github.com/users/bgrant0607/repos",
      "site_admin": false,
      "starred_url": "https://api.github.com/users/bgrant0607/starred{/owner}{/repo}",
      "subscriptions_url": "https://api.github.com/users/bgrant0607/subscriptions",
      "type": "User",
      "url": "https://api.github.com/users/bgrant0607"
    },
    "description": "https://github.com/kubernetes/features/blob/master/release-1.4/Release-1.4.md",
    "due_on": null,
    "html_url": "https://github.com/kubernetes/kubernetes/milestone/22",
    "id": 1777384,
    "labels_url": "https://api.github.com/repos/kubernetes/kubernetes/milestones/22/labels",
    "node_id": "MDk6TWlsZXN0b25lMTc3NzM4NA==",
    "number": 22,
    "open_issues": 0,
    "state": "closed",
    "title": "v1.4",
    "updated_at": "2019-08-26T17:23:33Z",
    "url": "https://api.github.com/repos/kubernetes/kubernetes/milestones/22"
  },
  "node_id": "MDU6SXNzdWUxNjM3NjUzMjc=",
  "number": 28481,
  "performed_via_github_app": null,
  "repository_url": "https://api.github.com/repos/kubernetes/kubernetes",
  "state": "closed",
  "title": "[Bug]Node status is OutOfDisk even has sufficient disk",
  "updated_at": "2016-07-07T00:59:17Z",
  "url": "https://api.github.com/repos/kubernetes/kubernetes/issues/28481",
  "user": {
    "avatar_url": "https://avatars0.githubusercontent.com/u/8870577?v=4",
    "events_url": "https://api.github.com/users/mdshuai/events{/privacy}",
    "followers_url": "https://api.github.com/users/mdshuai/followers",
    "following_url": "https://api.github.com/users/mdshuai/following{/other_user}",
    "gists_url": "https://api.github.com/users/mdshuai/gists{/gist_id}",
    "gravatar_id": "",
    "html_url": "https://github.com/mdshuai",
    "id": 8870577,
    "login": "mdshuai",
    "node_id": "MDQ6VXNlcjg4NzA1Nzc=",
    "organizations_url": "https://api.github.com/users/mdshuai/orgs",
    "received_events_url": "https://api.github.com/users/mdshuai/received_events",
    "repos_url": "https://api.github.com/users/mdshuai/repos",
    "site_admin": false,
    "starred_url": "https://api.github.com/users/mdshuai/starred{/owner}{/repo}",
    "subscriptions_url": "https://api.github.com/users/mdshuai/subscriptions",
    "type": "User",
    "url": "https://api.github.com/users/mdshuai"
  }
}