{
  "_links": {
    "comments": {
      "href": "https://api.github.com/repos/kubernetes/kubernetes/issues/94546/comments"
    },
    "commits": {
      "href": "https://api.github.com/repos/kubernetes/kubernetes/pulls/94546/commits"
    },
    "html": {
      "href": "https://github.com/kubernetes/kubernetes/pull/94546"
    },
    "issue": {
      "href": "https://api.github.com/repos/kubernetes/kubernetes/issues/94546"
    },
    "review_comment": {
      "href": "https://api.github.com/repos/kubernetes/kubernetes/pulls/comments{/number}"
    },
    "review_comments": {
      "href": "https://api.github.com/repos/kubernetes/kubernetes/pulls/94546/comments"
    },
    "self": {
      "href": "https://api.github.com/repos/kubernetes/kubernetes/pulls/94546"
    },
    "statuses": {
      "href": "https://api.github.com/repos/kubernetes/kubernetes/statuses/9c4f8ad9beb848365c48c04212d4e3d3478646b3"
    }
  },
  "active_lock_reason": null,
  "additions": 666,
  "assignee": {
    "avatar_url": "https://avatars0.githubusercontent.com/u/40677631?v=4",
    "events_url": "https://api.github.com/users/M00nF1sh/events{/privacy}",
    "followers_url": "https://api.github.com/users/M00nF1sh/followers",
    "following_url": "https://api.github.com/users/M00nF1sh/following{/other_user}",
    "gists_url": "https://api.github.com/users/M00nF1sh/gists{/gist_id}",
    "gravatar_id": "",
    "html_url": "https://github.com/M00nF1sh",
    "id": 40677631,
    "login": "M00nF1sh",
    "node_id": "MDQ6VXNlcjQwNjc3NjMx",
    "organizations_url": "https://api.github.com/users/M00nF1sh/orgs",
    "received_events_url": "https://api.github.com/users/M00nF1sh/received_events",
    "repos_url": "https://api.github.com/users/M00nF1sh/repos",
    "site_admin": false,
    "starred_url": "https://api.github.com/users/M00nF1sh/starred{/owner}{/repo}",
    "subscriptions_url": "https://api.github.com/users/M00nF1sh/subscriptions",
    "type": "User",
    "url": "https://api.github.com/users/M00nF1sh"
  },
  "assignees": [
    {
      "avatar_url": "https://avatars0.githubusercontent.com/u/40677631?v=4",
      "events_url": "https://api.github.com/users/M00nF1sh/events{/privacy}",
      "followers_url": "https://api.github.com/users/M00nF1sh/followers",
      "following_url": "https://api.github.com/users/M00nF1sh/following{/other_user}",
      "gists_url": "https://api.github.com/users/M00nF1sh/gists{/gist_id}",
      "gravatar_id": "",
      "html_url": "https://github.com/M00nF1sh",
      "id": 40677631,
      "login": "M00nF1sh",
      "node_id": "MDQ6VXNlcjQwNjc3NjMx",
      "organizations_url": "https://api.github.com/users/M00nF1sh/orgs",
      "received_events_url": "https://api.github.com/users/M00nF1sh/received_events",
      "repos_url": "https://api.github.com/users/M00nF1sh/repos",
      "site_admin": false,
      "starred_url": "https://api.github.com/users/M00nF1sh/starred{/owner}{/repo}",
      "subscriptions_url": "https://api.github.com/users/M00nF1sh/subscriptions",
      "type": "User",
      "url": "https://api.github.com/users/M00nF1sh"
    }
  ],
  "author_association": "CONTRIBUTOR",
  "base": {
    "label": "kubernetes:master",
    "ref": "master",
    "repo": {
      "archive_url": "https://api.github.com/repos/kubernetes/kubernetes/{archive_format}{/ref}",
      "archived": false,
      "assignees_url": "https://api.github.com/repos/kubernetes/kubernetes/assignees{/user}",
      "blobs_url": "https://api.github.com/repos/kubernetes/kubernetes/git/blobs{/sha}",
      "branches_url": "https://api.github.com/repos/kubernetes/kubernetes/branches{/branch}",
      "clone_url": "https://github.com/kubernetes/kubernetes.git",
      "collaborators_url": "https://api.github.com/repos/kubernetes/kubernetes/collaborators{/collaborator}",
      "comments_url": "https://api.github.com/repos/kubernetes/kubernetes/comments{/number}",
      "commits_url": "https://api.github.com/repos/kubernetes/kubernetes/commits{/sha}",
      "compare_url": "https://api.github.com/repos/kubernetes/kubernetes/compare/{base}...{head}",
      "contents_url": "https://api.github.com/repos/kubernetes/kubernetes/contents/{+path}",
      "contributors_url": "https://api.github.com/repos/kubernetes/kubernetes/contributors",
      "created_at": "2014-06-06T22:56:04Z",
      "default_branch": "master",
      "deployments_url": "https://api.github.com/repos/kubernetes/kubernetes/deployments",
      "description": "Production-Grade Container Scheduling and Management",
      "disabled": false,
      "downloads_url": "https://api.github.com/repos/kubernetes/kubernetes/downloads",
      "events_url": "https://api.github.com/repos/kubernetes/kubernetes/events",
      "fork": false,
      "forks": 25714,
      "forks_count": 25714,
      "forks_url": "https://api.github.com/repos/kubernetes/kubernetes/forks",
      "full_name": "kubernetes/kubernetes",
      "git_commits_url": "https://api.github.com/repos/kubernetes/kubernetes/git/commits{/sha}",
      "git_refs_url": "https://api.github.com/repos/kubernetes/kubernetes/git/refs{/sha}",
      "git_tags_url": "https://api.github.com/repos/kubernetes/kubernetes/git/tags{/sha}",
      "git_url": "git://github.com/kubernetes/kubernetes.git",
      "has_downloads": true,
      "has_issues": true,
      "has_pages": false,
      "has_projects": true,
      "has_wiki": false,
      "homepage": "https://kubernetes.io",
      "hooks_url": "https://api.github.com/repos/kubernetes/kubernetes/hooks",
      "html_url": "https://github.com/kubernetes/kubernetes",
      "id": 20580498,
      "issue_comment_url": "https://api.github.com/repos/kubernetes/kubernetes/issues/comments{/number}",
      "issue_events_url": "https://api.github.com/repos/kubernetes/kubernetes/issues/events{/number}",
      "issues_url": "https://api.github.com/repos/kubernetes/kubernetes/issues{/number}",
      "keys_url": "https://api.github.com/repos/kubernetes/kubernetes/keys{/key_id}",
      "labels_url": "https://api.github.com/repos/kubernetes/kubernetes/labels{/name}",
      "language": "Go",
      "languages_url": "https://api.github.com/repos/kubernetes/kubernetes/languages",
      "license": {
        "key": "apache-2.0",
        "name": "Apache License 2.0",
        "node_id": "MDc6TGljZW5zZTI=",
        "spdx_id": "Apache-2.0",
        "url": "https://api.github.com/licenses/apache-2.0"
      },
      "merges_url": "https://api.github.com/repos/kubernetes/kubernetes/merges",
      "milestones_url": "https://api.github.com/repos/kubernetes/kubernetes/milestones{/number}",
      "mirror_url": null,
      "name": "kubernetes",
      "node_id": "MDEwOlJlcG9zaXRvcnkyMDU4MDQ5OA==",
      "notifications_url": "https://api.github.com/repos/kubernetes/kubernetes/notifications{?since,all,participating}",
      "open_issues": 2874,
      "open_issues_count": 2874,
      "owner": {
        "avatar_url": "https://avatars2.githubusercontent.com/u/13629408?v=4",
        "events_url": "https://api.github.com/users/kubernetes/events{/privacy}",
        "followers_url": "https://api.github.com/users/kubernetes/followers",
        "following_url": "https://api.github.com/users/kubernetes/following{/other_user}",
        "gists_url": "https://api.github.com/users/kubernetes/gists{/gist_id}",
        "gravatar_id": "",
        "html_url": "https://github.com/kubernetes",
        "id": 13629408,
        "login": "kubernetes",
        "node_id": "MDEyOk9yZ2FuaXphdGlvbjEzNjI5NDA4",
        "organizations_url": "https://api.github.com/users/kubernetes/orgs",
        "received_events_url": "https://api.github.com/users/kubernetes/received_events",
        "repos_url": "https://api.github.com/users/kubernetes/repos",
        "site_admin": false,
        "starred_url": "https://api.github.com/users/kubernetes/starred{/owner}{/repo}",
        "subscriptions_url": "https://api.github.com/users/kubernetes/subscriptions",
        "type": "Organization",
        "url": "https://api.github.com/users/kubernetes"
      },
      "private": false,
      "pulls_url": "https://api.github.com/repos/kubernetes/kubernetes/pulls{/number}",
      "pushed_at": "2020-10-28T15:28:49Z",
      "releases_url": "https://api.github.com/repos/kubernetes/kubernetes/releases{/id}",
      "size": 938468,
      "ssh_url": "git@github.com:kubernetes/kubernetes.git",
      "stargazers_count": 71200,
      "stargazers_url": "https://api.github.com/repos/kubernetes/kubernetes/stargazers",
      "statuses_url": "https://api.github.com/repos/kubernetes/kubernetes/statuses/{sha}",
      "subscribers_url": "https://api.github.com/repos/kubernetes/kubernetes/subscribers",
      "subscription_url": "https://api.github.com/repos/kubernetes/kubernetes/subscription",
      "svn_url": "https://github.com/kubernetes/kubernetes",
      "tags_url": "https://api.github.com/repos/kubernetes/kubernetes/tags",
      "teams_url": "https://api.github.com/repos/kubernetes/kubernetes/teams",
      "trees_url": "https://api.github.com/repos/kubernetes/kubernetes/git/trees{/sha}",
      "updated_at": "2020-10-28T15:22:59Z",
      "url": "https://api.github.com/repos/kubernetes/kubernetes",
      "watchers": 71200,
      "watchers_count": 71200
    },
    "sha": "a84419f02766c2b8d6ce4a887f6fe45c6751d46e",
    "user": {
      "avatar_url": "https://avatars2.githubusercontent.com/u/13629408?v=4",
      "events_url": "https://api.github.com/users/kubernetes/events{/privacy}",
      "followers_url": "https://api.github.com/users/kubernetes/followers",
      "following_url": "https://api.github.com/users/kubernetes/following{/other_user}",
      "gists_url": "https://api.github.com/users/kubernetes/gists{/gist_id}",
      "gravatar_id": "",
      "html_url": "https://github.com/kubernetes",
      "id": 13629408,
      "login": "kubernetes",
      "node_id": "MDEyOk9yZ2FuaXphdGlvbjEzNjI5NDA4",
      "organizations_url": "https://api.github.com/users/kubernetes/orgs",
      "received_events_url": "https://api.github.com/users/kubernetes/received_events",
      "repos_url": "https://api.github.com/users/kubernetes/repos",
      "site_admin": false,
      "starred_url": "https://api.github.com/users/kubernetes/starred{/owner}{/repo}",
      "subscriptions_url": "https://api.github.com/users/kubernetes/subscriptions",
      "type": "Organization",
      "url": "https://api.github.com/users/kubernetes"
    }
  },
  "body": "<!--  Thanks for sending a pull request!  Here are some tips for you:\r\n\r\n1. If this is your first time, please read our contributor guidelines: https://git.k8s.io/community/contributors/guide/first-contribution.md#your-first-contribution and developer guide https://git.k8s.io/community/contributors/devel/development.md#development-guide\r\n2. Please label this pull request according to what type of issue you are addressing, especially if this is a release targeted pull request. For reference on required PR/issue labels, read here:\r\nhttps://git.k8s.io/community/contributors/devel/sig-release/release.md#issuepr-kind-label\r\n3. Ensure you have added or ran the appropriate tests for your PR: https://git.k8s.io/community/contributors/devel/sig-testing/testing.md\r\n4. If you want *faster* PR reviews, read how: https://git.k8s.io/community/contributors/guide/pull-requests.md#best-practices-for-faster-reviews\r\n5. If the PR is unfinished, see how to mark it: https://git.k8s.io/community/contributors/guide/pull-requests.md#marking-unfinished-pull-requests\r\n-->\r\n\r\n**What type of PR is this?**\r\n\r\n/kind feature\r\n\r\n**What this PR does / why we need it**:\r\nCurrently the AWS NLB uses hardcoded health check configuration. The classic LB also doesn't support configurable protocol/port/path for health check. This PR has support for additional service annotations to specify the health check protocol, port and the path for all supported LB types. The existing annotations for health check configurations are also honored for the NLB.\r\n* `service.beta.kubernetes.io/aws-load-balancer-healthcheck-protocol` to specify the protocol. Default is TCP for Local traffic policy and HTTP for cluster traffic policy. NLB allows TCP/HTTP/HTTPS, ELB allows TCP/SSL/HTTP/HTTPS. \r\n* `service.beta.kubernetes.io/aws-load-balancer-healthcheck-port` for the port. Defaults to `traffic-port` for Cluster, `healthCheckNodePort` for Local policy. \r\n* `service.beta.kubernetes.io/aws-load-balancer-healthcheck-path` specify the path for HTTP/HTTPS protocol. Default value is \"/\" for Cluster mode, \"/healthz\" for Local mode. If healthcheck protocol is TCP path gets ignored.\r\n\r\nNLB will also use the honor the interval and threshold annotations. \r\n\r\nIn case of NLB target groups, the protocol and interval configurations are not modifiable. So if changes to those params are detected, the existing target group gets deleted and re-created with the new health check config. \r\n\r\n**Which issue(s) this PR fixes**:\r\n<!--\r\n*Automatically closes linked issue when PR is merged.\r\nUsage: `Fixes #<issue number>`, or `Fixes (paste link of issue)`.\r\n_If PR is about `failing-tests or flakes`, please post the related issues/tests in a comment and do not use `Fixes`_*\r\n-->\r\nFixes #92321\r\nFixes #80996\r\nFixes #86624\r\nFixes #82595\r\nFixes #81469\r\n\r\n**Special notes for your reviewer**:\r\nTested via kops that the custom health check config gets honored for NLB/ELB, external traffic policy can be changed from Cluster to Local and vice versa. The AWS NLB doesn't support custom healthcheck timeout for TCP listeners, so default value gets used.\r\nTest summary\r\n* Without any annotations\r\n   - CLB cluster, TCP, traffic-port, default timeouts and thresholds\r\n   - CLB local, HTTP, path /healthz, health check node port, default timeouts and thresholds.\r\n   - NLB cluster, TCP, traffic-port, interval 30, thresholds (healthy/unhealthy) 3\r\n   - NLB local, HTTP, path /healthz, health check node port, interval 10, thresholds 2\r\n   - On modification of external traffic policy, health check of the resultant mode is configured. In case of NLB new target groups get created\r\n* With all health check annotations\r\n    - Health check configuration is based on the annotation values regardless of extrnal traffic policy for both NLB and CLB\r\n    - In case of NLB modification of protocol and interval values result in new target groups\r\n    - In case of NLB, timeout value gets ignored. Timeout is 6 seconds for HTTP, 10 seconds otherwise\r\n* Individual Health check annotations\r\n     - The remaining parameters take the default values\r\n     - CLB cluster, if health check protocol is HTTP, port is the traffic port, path is /, timeout 5s, interval 10s, unhealthy thr 6, healthy thr 2\r\n      - NLB local, if HC protocol is TCP, port is health check nodeport, interval 10s, healthy/unhealthy thresholds 2\r\n      - NLB cluster, if HC protocol is HTTP, port is traffic-port, interval 30, healthy/unhealthy thresholds 3\r\n      - NLB/CLB, path gets ignored for TCP\r\n* Mix of annotations\r\n      - Unspecified parameters take the default value\r\n      - HC annotations get honored switching from Local to Cluster external traffic policy\r\n      - For NLB, port, path and thresholds can be edited on the same target group\r\n      - For NLB, protocol and interval modification results in new target groups\r\n\r\n**Does this PR introduce a user-facing change?**:\r\n<!--\r\nIf no, just write \"NONE\" in the release-note block below.\r\nIf yes, a release note is required:\r\nEnter your extended release note in the block below. If the PR requires additional action from users switching to the new release, include the string \"action required\".\r\n\r\nFor more information on release notes see: https://git.k8s.io/community/contributors/guide/release-notes.md\r\n-->\r\n```release-note\r\nAllow configuring AWS LoadBalancer health check protocol via service annotations\r\n```\r\n\r\n**Additional documentation e.g., KEPs (Kubernetes Enhancement Proposals), usage docs, etc.**:\r\n\r\n<!--\r\nThis section can be blank if this pull request does not require a release note.\r\n\r\nWhen adding links which point to resources within git repositories, like\r\nKEPs or supporting documentation, please reference a specific commit and avoid\r\nlinking directly to the master branch. This ensures that links reference a\r\nspecific point in time, rather than a document that may change over time.\r\n\r\nSee here for guidance on getting permanent links to files: https://help.github.com/en/articles/getting-permanent-links-to-files\r\n\r\nPlease use the following format for linking documentation:\r\n- [KEP]: <link>\r\n- [Usage]: <link>\r\n- [Other doc]: <link>\r\n-->\r\n```docs\r\n\r\n```\r\n",
  "changed_files": 4,
  "closed_at": "2020-09-23T21:36:20Z",
  "comments": 12,
  "comments_url": "https://api.github.com/repos/kubernetes/kubernetes/issues/94546/comments",
  "commits": 1,
  "commits_url": "https://api.github.com/repos/kubernetes/kubernetes/pulls/94546/commits",
  "created_at": "2020-09-04T22:55:21Z",
  "deletions": 97,
  "diff_url": "https://github.com/kubernetes/kubernetes/pull/94546.diff",
  "draft": false,
  "head": {
    "label": "kishorj:nlb_custom_healthcheck",
    "ref": "nlb_custom_healthcheck",
    "repo": {
      "archive_url": "https://api.github.com/repos/kishorj/kubernetes/{archive_format}{/ref}",
      "archived": false,
      "assignees_url": "https://api.github.com/repos/kishorj/kubernetes/assignees{/user}",
      "blobs_url": "https://api.github.com/repos/kishorj/kubernetes/git/blobs{/sha}",
      "branches_url": "https://api.github.com/repos/kishorj/kubernetes/branches{/branch}",
      "clone_url": "https://github.com/kishorj/kubernetes.git",
      "collaborators_url": "https://api.github.com/repos/kishorj/kubernetes/collaborators{/collaborator}",
      "comments_url": "https://api.github.com/repos/kishorj/kubernetes/comments{/number}",
      "commits_url": "https://api.github.com/repos/kishorj/kubernetes/commits{/sha}",
      "compare_url": "https://api.github.com/repos/kishorj/kubernetes/compare/{base}...{head}",
      "contents_url": "https://api.github.com/repos/kishorj/kubernetes/contents/{+path}",
      "contributors_url": "https://api.github.com/repos/kishorj/kubernetes/contributors",
      "created_at": "2020-06-12T16:15:19Z",
      "default_branch": "master",
      "deployments_url": "https://api.github.com/repos/kishorj/kubernetes/deployments",
      "description": "Production-Grade Container Scheduling and Management",
      "disabled": false,
      "downloads_url": "https://api.github.com/repos/kishorj/kubernetes/downloads",
      "events_url": "https://api.github.com/repos/kishorj/kubernetes/events",
      "fork": true,
      "forks": 0,
      "forks_count": 0,
      "forks_url": "https://api.github.com/repos/kishorj/kubernetes/forks",
      "full_name": "kishorj/kubernetes",
      "git_commits_url": "https://api.github.com/repos/kishorj/kubernetes/git/commits{/sha}",
      "git_refs_url": "https://api.github.com/repos/kishorj/kubernetes/git/refs{/sha}",
      "git_tags_url": "https://api.github.com/repos/kishorj/kubernetes/git/tags{/sha}",
      "git_url": "git://github.com/kishorj/kubernetes.git",
      "has_downloads": true,
      "has_issues": false,
      "has_pages": false,
      "has_projects": true,
      "has_wiki": false,
      "homepage": "https://kubernetes.io",
      "hooks_url": "https://api.github.com/repos/kishorj/kubernetes/hooks",
      "html_url": "https://github.com/kishorj/kubernetes",
      "id": 271840633,
      "issue_comment_url": "https://api.github.com/repos/kishorj/kubernetes/issues/comments{/number}",
      "issue_events_url": "https://api.github.com/repos/kishorj/kubernetes/issues/events{/number}",
      "issues_url": "https://api.github.com/repos/kishorj/kubernetes/issues{/number}",
      "keys_url": "https://api.github.com/repos/kishorj/kubernetes/keys{/key_id}",
      "labels_url": "https://api.github.com/repos/kishorj/kubernetes/labels{/name}",
      "language": null,
      "languages_url": "https://api.github.com/repos/kishorj/kubernetes/languages",
      "license": {
        "key": "apache-2.0",
        "name": "Apache License 2.0",
        "node_id": "MDc6TGljZW5zZTI=",
        "spdx_id": "Apache-2.0",
        "url": "https://api.github.com/licenses/apache-2.0"
      },
      "merges_url": "https://api.github.com/repos/kishorj/kubernetes/merges",
      "milestones_url": "https://api.github.com/repos/kishorj/kubernetes/milestones{/number}",
      "mirror_url": null,
      "name": "kubernetes",
      "node_id": "MDEwOlJlcG9zaXRvcnkyNzE4NDA2MzM=",
      "notifications_url": "https://api.github.com/repos/kishorj/kubernetes/notifications{?since,all,participating}",
      "open_issues": 0,
      "open_issues_count": 0,
      "owner": {
        "avatar_url": "https://avatars3.githubusercontent.com/u/13045017?v=4",
        "events_url": "https://api.github.com/users/kishorj/events{/privacy}",
        "followers_url": "https://api.github.com/users/kishorj/followers",
        "following_url": "https://api.github.com/users/kishorj/following{/other_user}",
        "gists_url": "https://api.github.com/users/kishorj/gists{/gist_id}",
        "gravatar_id": "",
        "html_url": "https://github.com/kishorj",
        "id": 13045017,
        "login": "kishorj",
        "node_id": "MDQ6VXNlcjEzMDQ1MDE3",
        "organizations_url": "https://api.github.com/users/kishorj/orgs",
        "received_events_url": "https://api.github.com/users/kishorj/received_events",
        "repos_url": "https://api.github.com/users/kishorj/repos",
        "site_admin": false,
        "starred_url": "https://api.github.com/users/kishorj/starred{/owner}{/repo}",
        "subscriptions_url": "https://api.github.com/users/kishorj/subscriptions",
        "type": "User",
        "url": "https://api.github.com/users/kishorj"
      },
      "private": false,
      "pulls_url": "https://api.github.com/repos/kishorj/kubernetes/pulls{/number}",
      "pushed_at": "2020-10-02T03:34:16Z",
      "releases_url": "https://api.github.com/repos/kishorj/kubernetes/releases{/id}",
      "size": 717984,
      "ssh_url": "git@github.com:kishorj/kubernetes.git",
      "stargazers_count": 0,
      "stargazers_url": "https://api.github.com/repos/kishorj/kubernetes/stargazers",
      "statuses_url": "https://api.github.com/repos/kishorj/kubernetes/statuses/{sha}",
      "subscribers_url": "https://api.github.com/repos/kishorj/kubernetes/subscribers",
      "subscription_url": "https://api.github.com/repos/kishorj/kubernetes/subscription",
      "svn_url": "https://github.com/kishorj/kubernetes",
      "tags_url": "https://api.github.com/repos/kishorj/kubernetes/tags",
      "teams_url": "https://api.github.com/repos/kishorj/kubernetes/teams",
      "trees_url": "https://api.github.com/repos/kishorj/kubernetes/git/trees{/sha}",
      "updated_at": "2020-06-12T16:15:21Z",
      "url": "https://api.github.com/repos/kishorj/kubernetes",
      "watchers": 0,
      "watchers_count": 0
    },
    "sha": "9c4f8ad9beb848365c48c04212d4e3d3478646b3",
    "user": {
      "avatar_url": "https://avatars3.githubusercontent.com/u/13045017?v=4",
      "events_url": "https://api.github.com/users/kishorj/events{/privacy}",
      "followers_url": "https://api.github.com/users/kishorj/followers",
      "following_url": "https://api.github.com/users/kishorj/following{/other_user}",
      "gists_url": "https://api.github.com/users/kishorj/gists{/gist_id}",
      "gravatar_id": "",
      "html_url": "https://github.com/kishorj",
      "id": 13045017,
      "login": "kishorj",
      "node_id": "MDQ6VXNlcjEzMDQ1MDE3",
      "organizations_url": "https://api.github.com/users/kishorj/orgs",
      "received_events_url": "https://api.github.com/users/kishorj/received_events",
      "repos_url": "https://api.github.com/users/kishorj/repos",
      "site_admin": false,
      "starred_url": "https://api.github.com/users/kishorj/starred{/owner}{/repo}",
      "subscriptions_url": "https://api.github.com/users/kishorj/subscriptions",
      "type": "User",
      "url": "https://api.github.com/users/kishorj"
    }
  },
  "html_url": "https://github.com/kubernetes/kubernetes/pull/94546",
  "id": 480237348,
  "issue_url": "https://api.github.com/repos/kubernetes/kubernetes/issues/94546",
  "labels": [
    {
      "color": "0ffa16",
      "default": false,
      "description": "Indicates a PR has been approved by an approver from all required OWNERS files.",
      "id": 414883982,
      "name": "approved",
      "node_id": "MDU6TGFiZWw0MTQ4ODM5ODI=",
      "url": "https://api.github.com/repos/kubernetes/kubernetes/labels/approved"
    },
    {
      "color": "0052cc",
      "default": false,
      "description": null,
      "id": 154660912,
      "name": "area/cloudprovider",
      "node_id": "MDU6TGFiZWwxNTQ2NjA5MTI=",
      "url": "https://api.github.com/repos/kubernetes/kubernetes/labels/area/cloudprovider"
    },
    {
      "color": "bfe5bf",
      "default": false,
      "description": "Indicates the PR's author has signed the CNCF CLA.",
      "id": 477397086,
      "name": "cncf-cla: yes",
      "node_id": "MDU6TGFiZWw0NzczOTcwODY=",
      "url": "https://api.github.com/repos/kubernetes/kubernetes/labels/cncf-cla:%20yes"
    },
    {
      "color": "c7def8",
      "default": false,
      "description": "Categorizes issue or PR as related to a new feature.",
      "id": 267761362,
      "name": "kind/feature",
      "node_id": "MDU6TGFiZWwyNjc3NjEzNjI=",
      "url": "https://api.github.com/repos/kubernetes/kubernetes/labels/kind/feature"
    },
    {
      "color": "15dd18",
      "default": false,
      "description": "Indicates that a PR is ready to be merged.",
      "id": 148225179,
      "name": "lgtm",
      "node_id": "MDU6TGFiZWwxNDgyMjUxNzk=",
      "url": "https://api.github.com/repos/kubernetes/kubernetes/labels/lgtm"
    },
    {
      "color": "ededed",
      "default": false,
      "description": "Indicates a PR lacks a `priority/foo` label and requires one.",
      "id": 1111992057,
      "name": "needs-priority",
      "node_id": "MDU6TGFiZWwxMTExOTkyMDU3",
      "url": "https://api.github.com/repos/kubernetes/kubernetes/labels/needs-priority"
    },
    {
      "color": "15dd18",
      "default": false,
      "description": "Indicates a non-member PR verified by an org member that is safe to test.",
      "id": 1086787260,
      "name": "ok-to-test",
      "node_id": "MDU6TGFiZWwxMDg2Nzg3MjYw",
      "url": "https://api.github.com/repos/kubernetes/kubernetes/labels/ok-to-test"
    },
    {
      "color": "c2e0c6",
      "default": false,
      "description": "Denotes a PR that will be considered when it comes time to generate release notes.",
      "id": 200149833,
      "name": "release-note",
      "node_id": "MDU6TGFiZWwyMDAxNDk4MzM=",
      "url": "https://api.github.com/repos/kubernetes/kubernetes/labels/release-note"
    },
    {
      "color": "d2b48c",
      "default": false,
      "description": "Categorizes an issue or PR as relevant to SIG Cloud Provider.",
      "id": 958178286,
      "name": "sig/cloud-provider",
      "node_id": "MDU6TGFiZWw5NTgxNzgyODY=",
      "url": "https://api.github.com/repos/kubernetes/kubernetes/labels/sig/cloud-provider"
    },
    {
      "color": "ee5500",
      "default": false,
      "description": "Denotes a PR that changes 500-999 lines, ignoring generated files.",
      "id": 253451057,
      "name": "size/XL",
      "node_id": "MDU6TGFiZWwyNTM0NTEwNTc=",
      "url": "https://api.github.com/repos/kubernetes/kubernetes/labels/size/XL"
    }
  ],
  "linked_issue_numbers": [
    92321,
    80996,
    86624,
    82595,
    81469
  ],
  "locked": false,
  "maintainer_can_modify": false,
  "merge_commit_sha": "880344850d784e3ca7a19b454b394f34b8912204",
  "mergeable": null,
  "mergeable_state": "unknown",
  "merged": true,
  "merged_at": "2020-09-23T21:36:20Z",
  "merged_by": {
    "avatar_url": "https://avatars0.githubusercontent.com/u/20407524?v=4",
    "events_url": "https://api.github.com/users/k8s-ci-robot/events{/privacy}",
    "followers_url": "https://api.github.com/users/k8s-ci-robot/followers",
    "following_url": "https://api.github.com/users/k8s-ci-robot/following{/other_user}",
    "gists_url": "https://api.github.com/users/k8s-ci-robot/gists{/gist_id}",
    "gravatar_id": "",
    "html_url": "https://github.com/k8s-ci-robot",
    "id": 20407524,
    "login": "k8s-ci-robot",
    "node_id": "MDQ6VXNlcjIwNDA3NTI0",
    "organizations_url": "https://api.github.com/users/k8s-ci-robot/orgs",
    "received_events_url": "https://api.github.com/users/k8s-ci-robot/received_events",
    "repos_url": "https://api.github.com/users/k8s-ci-robot/repos",
    "site_admin": false,
    "starred_url": "https://api.github.com/users/k8s-ci-robot/starred{/owner}{/repo}",
    "subscriptions_url": "https://api.github.com/users/k8s-ci-robot/subscriptions",
    "type": "User",
    "url": "https://api.github.com/users/k8s-ci-robot"
  },
  "milestone": {
    "closed_at": null,
    "closed_issues": 784,
    "created_at": "2020-04-14T15:16:42Z",
    "creator": {
      "avatar_url": "https://avatars3.githubusercontent.com/u/567897?v=4",
      "events_url": "https://api.github.com/users/justaugustus/events{/privacy}",
      "followers_url": "https://api.github.com/users/justaugustus/followers",
      "following_url": "https://api.github.com/users/justaugustus/following{/other_user}",
      "gists_url": "https://api.github.com/users/justaugustus/gists{/gist_id}",
      "gravatar_id": "",
      "html_url": "https://github.com/justaugustus",
      "id": 567897,
      "login": "justaugustus",
      "node_id": "MDQ6VXNlcjU2Nzg5Nw==",
      "organizations_url": "https://api.github.com/users/justaugustus/orgs",
      "received_events_url": "https://api.github.com/users/justaugustus/received_events",
      "repos_url": "https://api.github.com/users/justaugustus/repos",
      "site_admin": false,
      "starred_url": "https://api.github.com/users/justaugustus/starred{/owner}{/repo}",
      "subscriptions_url": "https://api.github.com/users/justaugustus/subscriptions",
      "type": "User",
      "url": "https://api.github.com/users/justaugustus"
    },
    "description": "",
    "due_on": null,
    "html_url": "https://github.com/kubernetes/kubernetes/milestone/48",
    "id": 5307970,
    "labels_url": "https://api.github.com/repos/kubernetes/kubernetes/milestones/48/labels",
    "node_id": "MDk6TWlsZXN0b25lNTMwNzk3MA==",
    "number": 48,
    "open_issues": 94,
    "state": "open",
    "title": "v1.20",
    "updated_at": "2020-10-28T14:45:58Z",
    "url": "https://api.github.com/repos/kubernetes/kubernetes/milestones/48"
  },
  "node_id": "MDExOlB1bGxSZXF1ZXN0NDgwMjM3MzQ4",
  "number": 94546,
  "patch_url": "https://github.com/kubernetes/kubernetes/pull/94546.patch",
  "rebaseable": null,
  "requested_reviewers": [
    {
      "avatar_url": "https://avatars0.githubusercontent.com/u/278?v=4",
      "events_url": "https://api.github.com/users/gnufied/events{/privacy}",
      "followers_url": "https://api.github.com/users/gnufied/followers",
      "following_url": "https://api.github.com/users/gnufied/following{/other_user}",
      "gists_url": "https://api.github.com/users/gnufied/gists{/gist_id}",
      "gravatar_id": "",
      "html_url": "https://github.com/gnufied",
      "id": 278,
      "login": "gnufied",
      "node_id": "MDQ6VXNlcjI3OA==",
      "organizations_url": "https://api.github.com/users/gnufied/orgs",
      "received_events_url": "https://api.github.com/users/gnufied/received_events",
      "repos_url": "https://api.github.com/users/gnufied/repos",
      "site_admin": false,
      "starred_url": "https://api.github.com/users/gnufied/starred{/owner}{/repo}",
      "subscriptions_url": "https://api.github.com/users/gnufied/subscriptions",
      "type": "User",
      "url": "https://api.github.com/users/gnufied"
    },
    {
      "avatar_url": "https://avatars3.githubusercontent.com/u/791000?v=4",
      "events_url": "https://api.github.com/users/micahhausler/events{/privacy}",
      "followers_url": "https://api.github.com/users/micahhausler/followers",
      "following_url": "https://api.github.com/users/micahhausler/following{/other_user}",
      "gists_url": "https://api.github.com/users/micahhausler/gists{/gist_id}",
      "gravatar_id": "",
      "html_url": "https://github.com/micahhausler",
      "id": 791000,
      "login": "micahhausler",
      "node_id": "MDQ6VXNlcjc5MTAwMA==",
      "organizations_url": "https://api.github.com/users/micahhausler/orgs",
      "received_events_url": "https://api.github.com/users/micahhausler/received_events",
      "repos_url": "https://api.github.com/users/micahhausler/repos",
      "site_admin": false,
      "starred_url": "https://api.github.com/users/micahhausler/starred{/owner}{/repo}",
      "subscriptions_url": "https://api.github.com/users/micahhausler/subscriptions",
      "type": "User",
      "url": "https://api.github.com/users/micahhausler"
    }
  ],
  "requested_teams": [],
  "review_comment_url": "https://api.github.com/repos/kubernetes/kubernetes/pulls/comments{/number}",
  "review_comments": 0,
  "review_comments_url": "https://api.github.com/repos/kubernetes/kubernetes/pulls/94546/comments",
  "state": "closed",
  "statuses_url": "https://api.github.com/repos/kubernetes/kubernetes/statuses/9c4f8ad9beb848365c48c04212d4e3d3478646b3",
  "title": "AWS NLB/ELB health check config based on service annotations",
  "updated_at": "2020-09-30T23:50:48Z",
  "url": "https://api.github.com/repos/kubernetes/kubernetes/pulls/94546",
  "user": {
    "avatar_url": "https://avatars3.githubusercontent.com/u/13045017?v=4",
    "events_url": "https://api.github.com/users/kishorj/events{/privacy}",
    "followers_url": "https://api.github.com/users/kishorj/followers",
    "following_url": "https://api.github.com/users/kishorj/following{/other_user}",
    "gists_url": "https://api.github.com/users/kishorj/gists{/gist_id}",
    "gravatar_id": "",
    "html_url": "https://github.com/kishorj",
    "id": 13045017,
    "login": "kishorj",
    "node_id": "MDQ6VXNlcjEzMDQ1MDE3",
    "organizations_url": "https://api.github.com/users/kishorj/orgs",
    "received_events_url": "https://api.github.com/users/kishorj/received_events",
    "repos_url": "https://api.github.com/users/kishorj/repos",
    "site_admin": false,
    "starred_url": "https://api.github.com/users/kishorj/starred{/owner}{/repo}",
    "subscriptions_url": "https://api.github.com/users/kishorj/subscriptions",
    "type": "User",
    "url": "https://api.github.com/users/kishorj"
  }
}