{
  "_links": {
    "comments": {
      "href": "https://api.github.com/repos/kubernetes/kubernetes/issues/27943/comments"
    },
    "commits": {
      "href": "https://api.github.com/repos/kubernetes/kubernetes/pulls/27943/commits"
    },
    "html": {
      "href": "https://github.com/kubernetes/kubernetes/pull/27943"
    },
    "issue": {
      "href": "https://api.github.com/repos/kubernetes/kubernetes/issues/27943"
    },
    "review_comment": {
      "href": "https://api.github.com/repos/kubernetes/kubernetes/pulls/comments{/number}"
    },
    "review_comments": {
      "href": "https://api.github.com/repos/kubernetes/kubernetes/pulls/27943/comments"
    },
    "self": {
      "href": "https://api.github.com/repos/kubernetes/kubernetes/pulls/27943"
    },
    "statuses": {
      "href": "https://api.github.com/repos/kubernetes/kubernetes/statuses/5ed881c6c4d27885faebbd7563f0e0a5c51202a4"
    }
  },
  "active_lock_reason": null,
  "additions": 106,
  "assignee": {
    "avatar_url": "https://avatars0.githubusercontent.com/u/1163175?v=4",
    "events_url": "https://api.github.com/users/smarterclayton/events{/privacy}",
    "followers_url": "https://api.github.com/users/smarterclayton/followers",
    "following_url": "https://api.github.com/users/smarterclayton/following{/other_user}",
    "gists_url": "https://api.github.com/users/smarterclayton/gists{/gist_id}",
    "gravatar_id": "",
    "html_url": "https://github.com/smarterclayton",
    "id": 1163175,
    "login": "smarterclayton",
    "node_id": "MDQ6VXNlcjExNjMxNzU=",
    "organizations_url": "https://api.github.com/users/smarterclayton/orgs",
    "received_events_url": "https://api.github.com/users/smarterclayton/received_events",
    "repos_url": "https://api.github.com/users/smarterclayton/repos",
    "site_admin": false,
    "starred_url": "https://api.github.com/users/smarterclayton/starred{/owner}{/repo}",
    "subscriptions_url": "https://api.github.com/users/smarterclayton/subscriptions",
    "type": "User",
    "url": "https://api.github.com/users/smarterclayton"
  },
  "assignees": [
    {
      "avatar_url": "https://avatars0.githubusercontent.com/u/1163175?v=4",
      "events_url": "https://api.github.com/users/smarterclayton/events{/privacy}",
      "followers_url": "https://api.github.com/users/smarterclayton/followers",
      "following_url": "https://api.github.com/users/smarterclayton/following{/other_user}",
      "gists_url": "https://api.github.com/users/smarterclayton/gists{/gist_id}",
      "gravatar_id": "",
      "html_url": "https://github.com/smarterclayton",
      "id": 1163175,
      "login": "smarterclayton",
      "node_id": "MDQ6VXNlcjExNjMxNzU=",
      "organizations_url": "https://api.github.com/users/smarterclayton/orgs",
      "received_events_url": "https://api.github.com/users/smarterclayton/received_events",
      "repos_url": "https://api.github.com/users/smarterclayton/repos",
      "site_admin": false,
      "starred_url": "https://api.github.com/users/smarterclayton/starred{/owner}{/repo}",
      "subscriptions_url": "https://api.github.com/users/smarterclayton/subscriptions",
      "type": "User",
      "url": "https://api.github.com/users/smarterclayton"
    }
  ],
  "author_association": "MEMBER",
  "base": {
    "label": "kubernetes:master",
    "ref": "master",
    "repo": {
      "archive_url": "https://api.github.com/repos/kubernetes/kubernetes/{archive_format}{/ref}",
      "archived": false,
      "assignees_url": "https://api.github.com/repos/kubernetes/kubernetes/assignees{/user}",
      "blobs_url": "https://api.github.com/repos/kubernetes/kubernetes/git/blobs{/sha}",
      "branches_url": "https://api.github.com/repos/kubernetes/kubernetes/branches{/branch}",
      "clone_url": "https://github.com/kubernetes/kubernetes.git",
      "collaborators_url": "https://api.github.com/repos/kubernetes/kubernetes/collaborators{/collaborator}",
      "comments_url": "https://api.github.com/repos/kubernetes/kubernetes/comments{/number}",
      "commits_url": "https://api.github.com/repos/kubernetes/kubernetes/commits{/sha}",
      "compare_url": "https://api.github.com/repos/kubernetes/kubernetes/compare/{base}...{head}",
      "contents_url": "https://api.github.com/repos/kubernetes/kubernetes/contents/{+path}",
      "contributors_url": "https://api.github.com/repos/kubernetes/kubernetes/contributors",
      "created_at": "2014-06-06T22:56:04Z",
      "default_branch": "master",
      "deployments_url": "https://api.github.com/repos/kubernetes/kubernetes/deployments",
      "description": "Production-Grade Container Scheduling and Management",
      "disabled": false,
      "downloads_url": "https://api.github.com/repos/kubernetes/kubernetes/downloads",
      "events_url": "https://api.github.com/repos/kubernetes/kubernetes/events",
      "fork": false,
      "forks": 25710,
      "forks_count": 25710,
      "forks_url": "https://api.github.com/repos/kubernetes/kubernetes/forks",
      "full_name": "kubernetes/kubernetes",
      "git_commits_url": "https://api.github.com/repos/kubernetes/kubernetes/git/commits{/sha}",
      "git_refs_url": "https://api.github.com/repos/kubernetes/kubernetes/git/refs{/sha}",
      "git_tags_url": "https://api.github.com/repos/kubernetes/kubernetes/git/tags{/sha}",
      "git_url": "git://github.com/kubernetes/kubernetes.git",
      "has_downloads": true,
      "has_issues": true,
      "has_pages": false,
      "has_projects": true,
      "has_wiki": false,
      "homepage": "https://kubernetes.io",
      "hooks_url": "https://api.github.com/repos/kubernetes/kubernetes/hooks",
      "html_url": "https://github.com/kubernetes/kubernetes",
      "id": 20580498,
      "issue_comment_url": "https://api.github.com/repos/kubernetes/kubernetes/issues/comments{/number}",
      "issue_events_url": "https://api.github.com/repos/kubernetes/kubernetes/issues/events{/number}",
      "issues_url": "https://api.github.com/repos/kubernetes/kubernetes/issues{/number}",
      "keys_url": "https://api.github.com/repos/kubernetes/kubernetes/keys{/key_id}",
      "labels_url": "https://api.github.com/repos/kubernetes/kubernetes/labels{/name}",
      "language": "Go",
      "languages_url": "https://api.github.com/repos/kubernetes/kubernetes/languages",
      "license": {
        "key": "apache-2.0",
        "name": "Apache License 2.0",
        "node_id": "MDc6TGljZW5zZTI=",
        "spdx_id": "Apache-2.0",
        "url": "https://api.github.com/licenses/apache-2.0"
      },
      "merges_url": "https://api.github.com/repos/kubernetes/kubernetes/merges",
      "milestones_url": "https://api.github.com/repos/kubernetes/kubernetes/milestones{/number}",
      "mirror_url": null,
      "name": "kubernetes",
      "node_id": "MDEwOlJlcG9zaXRvcnkyMDU4MDQ5OA==",
      "notifications_url": "https://api.github.com/repos/kubernetes/kubernetes/notifications{?since,all,participating}",
      "open_issues": 2880,
      "open_issues_count": 2880,
      "owner": {
        "avatar_url": "https://avatars2.githubusercontent.com/u/13629408?v=4",
        "events_url": "https://api.github.com/users/kubernetes/events{/privacy}",
        "followers_url": "https://api.github.com/users/kubernetes/followers",
        "following_url": "https://api.github.com/users/kubernetes/following{/other_user}",
        "gists_url": "https://api.github.com/users/kubernetes/gists{/gist_id}",
        "gravatar_id": "",
        "html_url": "https://github.com/kubernetes",
        "id": 13629408,
        "login": "kubernetes",
        "node_id": "MDEyOk9yZ2FuaXphdGlvbjEzNjI5NDA4",
        "organizations_url": "https://api.github.com/users/kubernetes/orgs",
        "received_events_url": "https://api.github.com/users/kubernetes/received_events",
        "repos_url": "https://api.github.com/users/kubernetes/repos",
        "site_admin": false,
        "starred_url": "https://api.github.com/users/kubernetes/starred{/owner}{/repo}",
        "subscriptions_url": "https://api.github.com/users/kubernetes/subscriptions",
        "type": "Organization",
        "url": "https://api.github.com/users/kubernetes"
      },
      "private": false,
      "pulls_url": "https://api.github.com/repos/kubernetes/kubernetes/pulls{/number}",
      "pushed_at": "2020-10-28T03:44:11Z",
      "releases_url": "https://api.github.com/repos/kubernetes/kubernetes/releases{/id}",
      "size": 938453,
      "ssh_url": "git@github.com:kubernetes/kubernetes.git",
      "stargazers_count": 71181,
      "stargazers_url": "https://api.github.com/repos/kubernetes/kubernetes/stargazers",
      "statuses_url": "https://api.github.com/repos/kubernetes/kubernetes/statuses/{sha}",
      "subscribers_url": "https://api.github.com/repos/kubernetes/kubernetes/subscribers",
      "subscription_url": "https://api.github.com/repos/kubernetes/kubernetes/subscription",
      "svn_url": "https://github.com/kubernetes/kubernetes",
      "tags_url": "https://api.github.com/repos/kubernetes/kubernetes/tags",
      "teams_url": "https://api.github.com/repos/kubernetes/kubernetes/teams",
      "trees_url": "https://api.github.com/repos/kubernetes/kubernetes/git/trees{/sha}",
      "updated_at": "2020-10-28T04:14:27Z",
      "url": "https://api.github.com/repos/kubernetes/kubernetes",
      "watchers": 71181,
      "watchers_count": 71181
    },
    "sha": "c94976570fdf5bec60ce5cdd5d6edd56e1c62e25",
    "user": {
      "avatar_url": "https://avatars2.githubusercontent.com/u/13629408?v=4",
      "events_url": "https://api.github.com/users/kubernetes/events{/privacy}",
      "followers_url": "https://api.github.com/users/kubernetes/followers",
      "following_url": "https://api.github.com/users/kubernetes/following{/other_user}",
      "gists_url": "https://api.github.com/users/kubernetes/gists{/gist_id}",
      "gravatar_id": "",
      "html_url": "https://github.com/kubernetes",
      "id": 13629408,
      "login": "kubernetes",
      "node_id": "MDEyOk9yZ2FuaXphdGlvbjEzNjI5NDA4",
      "organizations_url": "https://api.github.com/users/kubernetes/orgs",
      "received_events_url": "https://api.github.com/users/kubernetes/received_events",
      "repos_url": "https://api.github.com/users/kubernetes/repos",
      "site_admin": false,
      "starred_url": "https://api.github.com/users/kubernetes/starred{/owner}{/repo}",
      "subscriptions_url": "https://api.github.com/users/kubernetes/subscriptions",
      "type": "Organization",
      "url": "https://api.github.com/users/kubernetes"
    }
  },
  "body": "<!--\nChecklist for submitting a Pull Request\n\nPlease remove this comment block before submitting.\n\n1. Please read our [contributor guidelines](https://github.com/kubernetes/kubernetes/blob/master/CONTRIBUTING.md).\n2. See our [developer guide](https://github.com/kubernetes/kubernetes/blob/master/docs/devel/development.md).\n3. If you want this PR to automatically close an issue when it is merged,\n   add `fixes #<issue number>` or `fixes #<issue number>, fixes #<issue number>`\n   to close multiple issues (see: https://github.com/blog/1506-closing-issues-via-pull-requests).\n4. Follow the instructions for [labeling and writing a release note for this PR](https://github.com/kubernetes/kubernetes/blob/master/docs/devel/pull-requests.md#release-notes) in the block below.\n-->\n\n[![Analytics](https://kubernetes-site.appspot.com/UA-36037335-10/GitHub/.github/PULL_REQUEST_TEMPLATE.md?pixel)]()\nFixes #21260\n",
  "changed_files": 10,
  "closed_at": "2016-07-14T15:03:40Z",
  "comments": 15,
  "comments_url": "https://api.github.com/repos/kubernetes/kubernetes/issues/27943/comments",
  "commits": 1,
  "commits_url": "https://api.github.com/repos/kubernetes/kubernetes/pulls/27943/commits",
  "created_at": "2016-06-23T15:11:01Z",
  "deletions": 48,
  "diff_url": "https://github.com/kubernetes/kubernetes/pull/27943.diff",
  "draft": false,
  "head": {
    "label": "ivan4th:refactor-printer-arguments",
    "ref": "refactor-printer-arguments",
    "repo": {
      "archive_url": "https://api.github.com/repos/ivan4th/kubernetes/{archive_format}{/ref}",
      "archived": false,
      "assignees_url": "https://api.github.com/repos/ivan4th/kubernetes/assignees{/user}",
      "blobs_url": "https://api.github.com/repos/ivan4th/kubernetes/git/blobs{/sha}",
      "branches_url": "https://api.github.com/repos/ivan4th/kubernetes/branches{/branch}",
      "clone_url": "https://github.com/ivan4th/kubernetes.git",
      "collaborators_url": "https://api.github.com/repos/ivan4th/kubernetes/collaborators{/collaborator}",
      "comments_url": "https://api.github.com/repos/ivan4th/kubernetes/comments{/number}",
      "commits_url": "https://api.github.com/repos/ivan4th/kubernetes/commits{/sha}",
      "compare_url": "https://api.github.com/repos/ivan4th/kubernetes/compare/{base}...{head}",
      "contents_url": "https://api.github.com/repos/ivan4th/kubernetes/contents/{+path}",
      "contributors_url": "https://api.github.com/repos/ivan4th/kubernetes/contributors",
      "created_at": "2016-06-23T10:49:36Z",
      "default_branch": "master",
      "deployments_url": "https://api.github.com/repos/ivan4th/kubernetes/deployments",
      "description": "Production-Grade Container Scheduling and Management",
      "disabled": false,
      "downloads_url": "https://api.github.com/repos/ivan4th/kubernetes/downloads",
      "events_url": "https://api.github.com/repos/ivan4th/kubernetes/events",
      "fork": true,
      "forks": 0,
      "forks_count": 0,
      "forks_url": "https://api.github.com/repos/ivan4th/kubernetes/forks",
      "full_name": "ivan4th/kubernetes",
      "git_commits_url": "https://api.github.com/repos/ivan4th/kubernetes/git/commits{/sha}",
      "git_refs_url": "https://api.github.com/repos/ivan4th/kubernetes/git/refs{/sha}",
      "git_tags_url": "https://api.github.com/repos/ivan4th/kubernetes/git/tags{/sha}",
      "git_url": "git://github.com/ivan4th/kubernetes.git",
      "has_downloads": true,
      "has_issues": false,
      "has_pages": false,
      "has_projects": true,
      "has_wiki": true,
      "homepage": "http://kubernetes.io",
      "hooks_url": "https://api.github.com/repos/ivan4th/kubernetes/hooks",
      "html_url": "https://github.com/ivan4th/kubernetes",
      "id": 61797759,
      "issue_comment_url": "https://api.github.com/repos/ivan4th/kubernetes/issues/comments{/number}",
      "issue_events_url": "https://api.github.com/repos/ivan4th/kubernetes/issues/events{/number}",
      "issues_url": "https://api.github.com/repos/ivan4th/kubernetes/issues{/number}",
      "keys_url": "https://api.github.com/repos/ivan4th/kubernetes/keys{/key_id}",
      "labels_url": "https://api.github.com/repos/ivan4th/kubernetes/labels{/name}",
      "language": "Go",
      "languages_url": "https://api.github.com/repos/ivan4th/kubernetes/languages",
      "license": {
        "key": "apache-2.0",
        "name": "Apache License 2.0",
        "node_id": "MDc6TGljZW5zZTI=",
        "spdx_id": "Apache-2.0",
        "url": "https://api.github.com/licenses/apache-2.0"
      },
      "merges_url": "https://api.github.com/repos/ivan4th/kubernetes/merges",
      "milestones_url": "https://api.github.com/repos/ivan4th/kubernetes/milestones{/number}",
      "mirror_url": null,
      "name": "kubernetes",
      "node_id": "MDEwOlJlcG9zaXRvcnk2MTc5Nzc1OQ==",
      "notifications_url": "https://api.github.com/repos/ivan4th/kubernetes/notifications{?since,all,participating}",
      "open_issues": 0,
      "open_issues_count": 0,
      "owner": {
        "avatar_url": "https://avatars2.githubusercontent.com/u/190448?v=4",
        "events_url": "https://api.github.com/users/ivan4th/events{/privacy}",
        "followers_url": "https://api.github.com/users/ivan4th/followers",
        "following_url": "https://api.github.com/users/ivan4th/following{/other_user}",
        "gists_url": "https://api.github.com/users/ivan4th/gists{/gist_id}",
        "gravatar_id": "",
        "html_url": "https://github.com/ivan4th",
        "id": 190448,
        "login": "ivan4th",
        "node_id": "MDQ6VXNlcjE5MDQ0OA==",
        "organizations_url": "https://api.github.com/users/ivan4th/orgs",
        "received_events_url": "https://api.github.com/users/ivan4th/received_events",
        "repos_url": "https://api.github.com/users/ivan4th/repos",
        "site_admin": false,
        "starred_url": "https://api.github.com/users/ivan4th/starred{/owner}{/repo}",
        "subscriptions_url": "https://api.github.com/users/ivan4th/subscriptions",
        "type": "User",
        "url": "https://api.github.com/users/ivan4th"
      },
      "private": false,
      "pulls_url": "https://api.github.com/repos/ivan4th/kubernetes/pulls{/number}",
      "pushed_at": "2019-10-11T19:36:32Z",
      "releases_url": "https://api.github.com/repos/ivan4th/kubernetes/releases{/id}",
      "size": 663202,
      "ssh_url": "git@github.com:ivan4th/kubernetes.git",
      "stargazers_count": 0,
      "stargazers_url": "https://api.github.com/repos/ivan4th/kubernetes/stargazers",
      "statuses_url": "https://api.github.com/repos/ivan4th/kubernetes/statuses/{sha}",
      "subscribers_url": "https://api.github.com/repos/ivan4th/kubernetes/subscribers",
      "subscription_url": "https://api.github.com/repos/ivan4th/kubernetes/subscription",
      "svn_url": "https://github.com/ivan4th/kubernetes",
      "tags_url": "https://api.github.com/repos/ivan4th/kubernetes/tags",
      "teams_url": "https://api.github.com/repos/ivan4th/kubernetes/teams",
      "trees_url": "https://api.github.com/repos/ivan4th/kubernetes/git/trees{/sha}",
      "updated_at": "2016-06-23T10:49:53Z",
      "url": "https://api.github.com/repos/ivan4th/kubernetes",
      "watchers": 0,
      "watchers_count": 0
    },
    "sha": "5ed881c6c4d27885faebbd7563f0e0a5c51202a4",
    "user": {
      "avatar_url": "https://avatars2.githubusercontent.com/u/190448?v=4",
      "events_url": "https://api.github.com/users/ivan4th/events{/privacy}",
      "followers_url": "https://api.github.com/users/ivan4th/followers",
      "following_url": "https://api.github.com/users/ivan4th/following{/other_user}",
      "gists_url": "https://api.github.com/users/ivan4th/gists{/gist_id}",
      "gravatar_id": "",
      "html_url": "https://github.com/ivan4th",
      "id": 190448,
      "login": "ivan4th",
      "node_id": "MDQ6VXNlcjE5MDQ0OA==",
      "organizations_url": "https://api.github.com/users/ivan4th/orgs",
      "received_events_url": "https://api.github.com/users/ivan4th/received_events",
      "repos_url": "https://api.github.com/users/ivan4th/repos",
      "site_admin": false,
      "starred_url": "https://api.github.com/users/ivan4th/starred{/owner}{/repo}",
      "subscriptions_url": "https://api.github.com/users/ivan4th/subscriptions",
      "type": "User",
      "url": "https://api.github.com/users/ivan4th"
    }
  },
  "html_url": "https://github.com/kubernetes/kubernetes/pull/27943",
  "id": 74972319,
  "issue_url": "https://api.github.com/repos/kubernetes/kubernetes/issues/27943",
  "labels": [
    {
      "color": "0052cc",
      "default": false,
      "description": null,
      "id": 138247961,
      "name": "area/kubectl",
      "node_id": "MDU6TGFiZWwxMzgyNDc5NjE=",
      "url": "https://api.github.com/repos/kubernetes/kubernetes/labels/area/kubectl"
    },
    {
      "color": "15dd18",
      "default": false,
      "description": "Indicates that a PR is ready to be merged.",
      "id": 148225179,
      "name": "lgtm",
      "node_id": "MDU6TGFiZWwxNDgyMjUxNzk=",
      "url": "https://api.github.com/repos/kubernetes/kubernetes/labels/lgtm"
    },
    {
      "color": "c2e0c6",
      "default": false,
      "description": "Denotes a PR that doesn't merit a release note.",
      "id": 349530249,
      "name": "release-note-none",
      "node_id": "MDU6TGFiZWwzNDk1MzAyNDk=",
      "url": "https://api.github.com/repos/kubernetes/kubernetes/labels/release-note-none"
    },
    {
      "color": "ee9900",
      "default": false,
      "description": "Denotes a PR that changes 100-499 lines, ignoring generated files.",
      "id": 253450978,
      "name": "size/L",
      "node_id": "MDU6TGFiZWwyNTM0NTA5Nzg=",
      "url": "https://api.github.com/repos/kubernetes/kubernetes/labels/size/L"
    }
  ],
  "linked_issue_numbers": [
    21260
  ],
  "locked": false,
  "maintainer_can_modify": false,
  "merge_commit_sha": "98d769cf3de1dec2eb1b4a4579d7c07a82e6c17a",
  "mergeable": null,
  "mergeable_state": "unknown",
  "merged": true,
  "merged_at": "2016-07-14T15:03:40Z",
  "merged_by": {
    "avatar_url": "https://avatars0.githubusercontent.com/u/13653959?v=4",
    "events_url": "https://api.github.com/users/k8s-github-robot/events{/privacy}",
    "followers_url": "https://api.github.com/users/k8s-github-robot/followers",
    "following_url": "https://api.github.com/users/k8s-github-robot/following{/other_user}",
    "gists_url": "https://api.github.com/users/k8s-github-robot/gists{/gist_id}",
    "gravatar_id": "",
    "html_url": "https://github.com/k8s-github-robot",
    "id": 13653959,
    "login": "k8s-github-robot",
    "node_id": "MDQ6VXNlcjEzNjUzOTU5",
    "organizations_url": "https://api.github.com/users/k8s-github-robot/orgs",
    "received_events_url": "https://api.github.com/users/k8s-github-robot/received_events",
    "repos_url": "https://api.github.com/users/k8s-github-robot/repos",
    "site_admin": false,
    "starred_url": "https://api.github.com/users/k8s-github-robot/starred{/owner}{/repo}",
    "subscriptions_url": "https://api.github.com/users/k8s-github-robot/subscriptions",
    "type": "User",
    "url": "https://api.github.com/users/k8s-github-robot"
  },
  "milestone": null,
  "node_id": "MDExOlB1bGxSZXF1ZXN0NzQ5NzIzMTk=",
  "number": 27943,
  "patch_url": "https://github.com/kubernetes/kubernetes/pull/27943.patch",
  "rebaseable": null,
  "requested_reviewers": [],
  "requested_teams": [],
  "review_comment_url": "https://api.github.com/repos/kubernetes/kubernetes/pulls/comments{/number}",
  "review_comments": 0,
  "review_comments_url": "https://api.github.com/repos/kubernetes/kubernetes/pulls/27943/comments",
  "state": "closed",
  "statuses_url": "https://api.github.com/repos/kubernetes/kubernetes/statuses/5ed881c6c4d27885faebbd7563f0e0a5c51202a4",
  "title": "Refactor Printer arguments",
  "updated_at": "2016-07-14T15:34:12Z",
  "url": "https://api.github.com/repos/kubernetes/kubernetes/pulls/27943",
  "user": {
    "avatar_url": "https://avatars2.githubusercontent.com/u/190448?v=4",
    "events_url": "https://api.github.com/users/ivan4th/events{/privacy}",
    "followers_url": "https://api.github.com/users/ivan4th/followers",
    "following_url": "https://api.github.com/users/ivan4th/following{/other_user}",
    "gists_url": "https://api.github.com/users/ivan4th/gists{/gist_id}",
    "gravatar_id": "",
    "html_url": "https://github.com/ivan4th",
    "id": 190448,
    "login": "ivan4th",
    "node_id": "MDQ6VXNlcjE5MDQ0OA==",
    "organizations_url": "https://api.github.com/users/ivan4th/orgs",
    "received_events_url": "https://api.github.com/users/ivan4th/received_events",
    "repos_url": "https://api.github.com/users/ivan4th/repos",
    "site_admin": false,
    "starred_url": "https://api.github.com/users/ivan4th/starred{/owner}{/repo}",
    "subscriptions_url": "https://api.github.com/users/ivan4th/subscriptions",
    "type": "User",
    "url": "https://api.github.com/users/ivan4th"
  }
}