{
  "_links": {
    "comments": {
      "href": "https://api.github.com/repos/rook/rook/issues/3061/comments"
    },
    "commits": {
      "href": "https://api.github.com/repos/rook/rook/pulls/3061/commits"
    },
    "html": {
      "href": "https://github.com/rook/rook/pull/3061"
    },
    "issue": {
      "href": "https://api.github.com/repos/rook/rook/issues/3061"
    },
    "review_comment": {
      "href": "https://api.github.com/repos/rook/rook/pulls/comments{/number}"
    },
    "review_comments": {
      "href": "https://api.github.com/repos/rook/rook/pulls/3061/comments"
    },
    "self": {
      "href": "https://api.github.com/repos/rook/rook/pulls/3061"
    },
    "statuses": {
      "href": "https://api.github.com/repos/rook/rook/statuses/81f55a12eb8b7f2c8af74431f20861520bf2c8db"
    }
  },
  "active_lock_reason": null,
  "additions": 17,
  "assignee": null,
  "assignees": [],
  "author_association": "MEMBER",
  "base": {
    "label": "rook:master",
    "ref": "master",
    "repo": {
      "archive_url": "https://api.github.com/repos/rook/rook/{archive_format}{/ref}",
      "archived": false,
      "assignees_url": "https://api.github.com/repos/rook/rook/assignees{/user}",
      "blobs_url": "https://api.github.com/repos/rook/rook/git/blobs{/sha}",
      "branches_url": "https://api.github.com/repos/rook/rook/branches{/branch}",
      "clone_url": "https://github.com/rook/rook.git",
      "collaborators_url": "https://api.github.com/repos/rook/rook/collaborators{/collaborator}",
      "comments_url": "https://api.github.com/repos/rook/rook/comments{/number}",
      "commits_url": "https://api.github.com/repos/rook/rook/commits{/sha}",
      "compare_url": "https://api.github.com/repos/rook/rook/compare/{base}...{head}",
      "contents_url": "https://api.github.com/repos/rook/rook/contents/{+path}",
      "contributors_url": "https://api.github.com/repos/rook/rook/contributors",
      "created_at": "2016-07-08T22:45:05Z",
      "default_branch": "master",
      "deployments_url": "https://api.github.com/repos/rook/rook/deployments",
      "description": "Storage Orchestration for Kubernetes",
      "disabled": false,
      "downloads_url": "https://api.github.com/repos/rook/rook/downloads",
      "events_url": "https://api.github.com/repos/rook/rook/events",
      "fork": false,
      "forks": 1652,
      "forks_count": 1652,
      "forks_url": "https://api.github.com/repos/rook/rook/forks",
      "full_name": "rook/rook",
      "git_commits_url": "https://api.github.com/repos/rook/rook/git/commits{/sha}",
      "git_refs_url": "https://api.github.com/repos/rook/rook/git/refs{/sha}",
      "git_tags_url": "https://api.github.com/repos/rook/rook/git/tags{/sha}",
      "git_url": "git://github.com/rook/rook.git",
      "has_downloads": true,
      "has_issues": true,
      "has_pages": false,
      "has_projects": true,
      "has_wiki": true,
      "homepage": "https://rook.io",
      "hooks_url": "https://api.github.com/repos/rook/rook/hooks",
      "html_url": "https://github.com/rook/rook",
      "id": 62921553,
      "issue_comment_url": "https://api.github.com/repos/rook/rook/issues/comments{/number}",
      "issue_events_url": "https://api.github.com/repos/rook/rook/issues/events{/number}",
      "issues_url": "https://api.github.com/repos/rook/rook/issues{/number}",
      "keys_url": "https://api.github.com/repos/rook/rook/keys{/key_id}",
      "labels_url": "https://api.github.com/repos/rook/rook/labels{/name}",
      "language": "Go",
      "languages_url": "https://api.github.com/repos/rook/rook/languages",
      "license": {
        "key": "apache-2.0",
        "name": "Apache License 2.0",
        "node_id": "MDc6TGljZW5zZTI=",
        "spdx_id": "Apache-2.0",
        "url": "https://api.github.com/licenses/apache-2.0"
      },
      "merges_url": "https://api.github.com/repos/rook/rook/merges",
      "milestones_url": "https://api.github.com/repos/rook/rook/milestones{/number}",
      "mirror_url": null,
      "name": "rook",
      "node_id": "MDEwOlJlcG9zaXRvcnk2MjkyMTU1Mw==",
      "notifications_url": "https://api.github.com/repos/rook/rook/notifications{?since,all,participating}",
      "open_issues": 232,
      "open_issues_count": 232,
      "owner": {
        "avatar_url": "https://avatars1.githubusercontent.com/u/22860722?v=4",
        "events_url": "https://api.github.com/users/rook/events{/privacy}",
        "followers_url": "https://api.github.com/users/rook/followers",
        "following_url": "https://api.github.com/users/rook/following{/other_user}",
        "gists_url": "https://api.github.com/users/rook/gists{/gist_id}",
        "gravatar_id": "",
        "html_url": "https://github.com/rook",
        "id": 22860722,
        "login": "rook",
        "node_id": "MDEyOk9yZ2FuaXphdGlvbjIyODYwNzIy",
        "organizations_url": "https://api.github.com/users/rook/orgs",
        "received_events_url": "https://api.github.com/users/rook/received_events",
        "repos_url": "https://api.github.com/users/rook/repos",
        "site_admin": false,
        "starred_url": "https://api.github.com/users/rook/starred{/owner}{/repo}",
        "subscriptions_url": "https://api.github.com/users/rook/subscriptions",
        "type": "Organization",
        "url": "https://api.github.com/users/rook"
      },
      "private": false,
      "pulls_url": "https://api.github.com/repos/rook/rook/pulls{/number}",
      "pushed_at": "2020-10-28T00:36:56Z",
      "releases_url": "https://api.github.com/repos/rook/rook/releases{/id}",
      "size": 37445,
      "ssh_url": "git@github.com:rook/rook.git",
      "stargazers_count": 7863,
      "stargazers_url": "https://api.github.com/repos/rook/rook/stargazers",
      "statuses_url": "https://api.github.com/repos/rook/rook/statuses/{sha}",
      "subscribers_url": "https://api.github.com/repos/rook/rook/subscribers",
      "subscription_url": "https://api.github.com/repos/rook/rook/subscription",
      "svn_url": "https://github.com/rook/rook",
      "tags_url": "https://api.github.com/repos/rook/rook/tags",
      "teams_url": "https://api.github.com/repos/rook/rook/teams",
      "trees_url": "https://api.github.com/repos/rook/rook/git/trees{/sha}",
      "updated_at": "2020-10-28T04:16:55Z",
      "url": "https://api.github.com/repos/rook/rook",
      "watchers": 7863,
      "watchers_count": 7863
    },
    "sha": "9cf586968ad5b3424ba0036792bd488c4653deb0",
    "user": {
      "avatar_url": "https://avatars1.githubusercontent.com/u/22860722?v=4",
      "events_url": "https://api.github.com/users/rook/events{/privacy}",
      "followers_url": "https://api.github.com/users/rook/followers",
      "following_url": "https://api.github.com/users/rook/following{/other_user}",
      "gists_url": "https://api.github.com/users/rook/gists{/gist_id}",
      "gravatar_id": "",
      "html_url": "https://github.com/rook",
      "id": 22860722,
      "login": "rook",
      "node_id": "MDEyOk9yZ2FuaXphdGlvbjIyODYwNzIy",
      "organizations_url": "https://api.github.com/users/rook/orgs",
      "received_events_url": "https://api.github.com/users/rook/received_events",
      "repos_url": "https://api.github.com/users/rook/repos",
      "site_admin": false,
      "starred_url": "https://api.github.com/users/rook/starred{/owner}{/repo}",
      "subscriptions_url": "https://api.github.com/users/rook/subscriptions",
      "type": "Organization",
      "url": "https://api.github.com/users/rook"
    }
  },
  "body": "Signed-off-by: travisn <tnielsen@redhat.com>\r\n\r\n<!-- Please take a look at our [Contributing](https://rook.io/docs/rook/master/development-flow.html)\r\ndocumentation before submitting a Pull Request!\r\nThank you for contributing to Rook! -->\r\n\r\n**Description of your changes:**\r\nThe `alpha`, `beta`, and `stable` channels do not match the rook release process. Each storage provider defines their own stability based on the CRDs rather than defining it with the release process. Rook really only has two release streams: master and the official releases. Master is published with each merge, while releases go through a signoff process to ensure quality. Thus, the `alpha`, `beta`, and `stable` channels are removed and replaced with a single `release` channel. See [the detailed notes on this change](https://github.com/rook/rook/issues/1885#issuecomment-460444455).\r\n\r\nThe `release` channel is only used for promoting the helm chart. The docker images do not receive a channel tag so the versioning can be controlled very carefully for the stateful upgrades.\r\n\r\n@bassam @jbw976 PTAL\r\n\r\n**Which issue is resolved by this Pull Request:**\r\nResolves #1885\r\n\r\n**Checklist:**\r\n- [x] Documentation has been updated, if necessary.\r\n- [x] Pending release notes updated with breaking and/or notable changes, if necessary.\r\n- [ ] Upgrade from previous release is tested and upgrade user guide is updated, if necessary.\r\n- [ ] Code generation (`make codegen`) has been run to update object specifications, if necessary.\r\n- [ ] Comments have been added or updated based on the standards set in [CONTRIBUTING.md](../blob/master/CONTRIBUTING.md#comments)\r\n",
  "changed_files": 5,
  "closed_at": "2019-04-28T23:06:00Z",
  "comments": 4,
  "comments_url": "https://api.github.com/repos/rook/rook/issues/3061/comments",
  "commits": 1,
  "commits_url": "https://api.github.com/repos/rook/rook/pulls/3061/commits",
  "created_at": "2019-04-26T04:59:57Z",
  "deletions": 30,
  "diff_url": "https://github.com/rook/rook/pull/3061.diff",
  "draft": false,
  "head": {
    "label": "travisn:update-channels",
    "ref": "update-channels",
    "repo": {
      "archive_url": "https://api.github.com/repos/travisn/rook/{archive_format}{/ref}",
      "archived": false,
      "assignees_url": "https://api.github.com/repos/travisn/rook/assignees{/user}",
      "blobs_url": "https://api.github.com/repos/travisn/rook/git/blobs{/sha}",
      "branches_url": "https://api.github.com/repos/travisn/rook/branches{/branch}",
      "clone_url": "https://github.com/travisn/rook.git",
      "collaborators_url": "https://api.github.com/repos/travisn/rook/collaborators{/collaborator}",
      "comments_url": "https://api.github.com/repos/travisn/rook/comments{/number}",
      "commits_url": "https://api.github.com/repos/travisn/rook/commits{/sha}",
      "compare_url": "https://api.github.com/repos/travisn/rook/compare/{base}...{head}",
      "contents_url": "https://api.github.com/repos/travisn/rook/contents/{+path}",
      "contributors_url": "https://api.github.com/repos/travisn/rook/contributors",
      "created_at": "2016-11-08T08:30:24Z",
      "default_branch": "master",
      "deployments_url": "https://api.github.com/repos/travisn/rook/deployments",
      "description": "Open, Universal, Cloud Native, Distributed Storage",
      "disabled": false,
      "downloads_url": "https://api.github.com/repos/travisn/rook/downloads",
      "events_url": "https://api.github.com/repos/travisn/rook/events",
      "fork": true,
      "forks": 3,
      "forks_count": 3,
      "forks_url": "https://api.github.com/repos/travisn/rook/forks",
      "full_name": "travisn/rook",
      "git_commits_url": "https://api.github.com/repos/travisn/rook/git/commits{/sha}",
      "git_refs_url": "https://api.github.com/repos/travisn/rook/git/refs{/sha}",
      "git_tags_url": "https://api.github.com/repos/travisn/rook/git/tags{/sha}",
      "git_url": "git://github.com/travisn/rook.git",
      "has_downloads": true,
      "has_issues": false,
      "has_pages": false,
      "has_projects": true,
      "has_wiki": true,
      "homepage": "http://rook.io",
      "hooks_url": "https://api.github.com/repos/travisn/rook/hooks",
      "html_url": "https://github.com/travisn/rook",
      "id": 73165238,
      "issue_comment_url": "https://api.github.com/repos/travisn/rook/issues/comments{/number}",
      "issue_events_url": "https://api.github.com/repos/travisn/rook/issues/events{/number}",
      "issues_url": "https://api.github.com/repos/travisn/rook/issues{/number}",
      "keys_url": "https://api.github.com/repos/travisn/rook/keys{/key_id}",
      "labels_url": "https://api.github.com/repos/travisn/rook/labels{/name}",
      "language": "Go",
      "languages_url": "https://api.github.com/repos/travisn/rook/languages",
      "license": {
        "key": "apache-2.0",
        "name": "Apache License 2.0",
        "node_id": "MDc6TGljZW5zZTI=",
        "spdx_id": "Apache-2.0",
        "url": "https://api.github.com/licenses/apache-2.0"
      },
      "merges_url": "https://api.github.com/repos/travisn/rook/merges",
      "milestones_url": "https://api.github.com/repos/travisn/rook/milestones{/number}",
      "mirror_url": null,
      "name": "rook",
      "node_id": "MDEwOlJlcG9zaXRvcnk3MzE2NTIzOA==",
      "notifications_url": "https://api.github.com/repos/travisn/rook/notifications{?since,all,participating}",
      "open_issues": 0,
      "open_issues_count": 0,
      "owner": {
        "avatar_url": "https://avatars0.githubusercontent.com/u/1048514?v=4",
        "events_url": "https://api.github.com/users/travisn/events{/privacy}",
        "followers_url": "https://api.github.com/users/travisn/followers",
        "following_url": "https://api.github.com/users/travisn/following{/other_user}",
        "gists_url": "https://api.github.com/users/travisn/gists{/gist_id}",
        "gravatar_id": "",
        "html_url": "https://github.com/travisn",
        "id": 1048514,
        "login": "travisn",
        "node_id": "MDQ6VXNlcjEwNDg1MTQ=",
        "organizations_url": "https://api.github.com/users/travisn/orgs",
        "received_events_url": "https://api.github.com/users/travisn/received_events",
        "repos_url": "https://api.github.com/users/travisn/repos",
        "site_admin": false,
        "starred_url": "https://api.github.com/users/travisn/starred{/owner}{/repo}",
        "subscriptions_url": "https://api.github.com/users/travisn/subscriptions",
        "type": "User",
        "url": "https://api.github.com/users/travisn"
      },
      "private": false,
      "pulls_url": "https://api.github.com/repos/travisn/rook/pulls{/number}",
      "pushed_at": "2020-10-27T15:16:02Z",
      "releases_url": "https://api.github.com/repos/travisn/rook/releases{/id}",
      "size": 35830,
      "ssh_url": "git@github.com:travisn/rook.git",
      "stargazers_count": 2,
      "stargazers_url": "https://api.github.com/repos/travisn/rook/stargazers",
      "statuses_url": "https://api.github.com/repos/travisn/rook/statuses/{sha}",
      "subscribers_url": "https://api.github.com/repos/travisn/rook/subscribers",
      "subscription_url": "https://api.github.com/repos/travisn/rook/subscription",
      "svn_url": "https://github.com/travisn/rook",
      "tags_url": "https://api.github.com/repos/travisn/rook/tags",
      "teams_url": "https://api.github.com/repos/travisn/rook/teams",
      "trees_url": "https://api.github.com/repos/travisn/rook/git/trees{/sha}",
      "updated_at": "2020-10-26T19:46:36Z",
      "url": "https://api.github.com/repos/travisn/rook",
      "watchers": 2,
      "watchers_count": 2
    },
    "sha": "81f55a12eb8b7f2c8af74431f20861520bf2c8db",
    "user": {
      "avatar_url": "https://avatars0.githubusercontent.com/u/1048514?v=4",
      "events_url": "https://api.github.com/users/travisn/events{/privacy}",
      "followers_url": "https://api.github.com/users/travisn/followers",
      "following_url": "https://api.github.com/users/travisn/following{/other_user}",
      "gists_url": "https://api.github.com/users/travisn/gists{/gist_id}",
      "gravatar_id": "",
      "html_url": "https://github.com/travisn",
      "id": 1048514,
      "login": "travisn",
      "node_id": "MDQ6VXNlcjEwNDg1MTQ=",
      "organizations_url": "https://api.github.com/users/travisn/orgs",
      "received_events_url": "https://api.github.com/users/travisn/received_events",
      "repos_url": "https://api.github.com/users/travisn/repos",
      "site_admin": false,
      "starred_url": "https://api.github.com/users/travisn/starred{/owner}{/repo}",
      "subscriptions_url": "https://api.github.com/users/travisn/subscriptions",
      "type": "User",
      "url": "https://api.github.com/users/travisn"
    }
  },
  "html_url": "https://github.com/rook/rook/pull/3061",
  "id": 273761664,
  "issue_url": "https://api.github.com/repos/rook/rook/issues/3061",
  "labels": [],
  "linked_issue_numbers": [
    1885
  ],
  "locked": false,
  "maintainer_can_modify": false,
  "merge_commit_sha": "b35615f75b11b7396cabebecfb13f5e5b1aeddb1",
  "mergeable": null,
  "mergeable_state": "unknown",
  "merged": true,
  "merged_at": "2019-04-28T23:06:00Z",
  "merged_by": {
    "avatar_url": "https://avatars3.githubusercontent.com/u/1463491?v=4",
    "events_url": "https://api.github.com/users/bassam/events{/privacy}",
    "followers_url": "https://api.github.com/users/bassam/followers",
    "following_url": "https://api.github.com/users/bassam/following{/other_user}",
    "gists_url": "https://api.github.com/users/bassam/gists{/gist_id}",
    "gravatar_id": "",
    "html_url": "https://github.com/bassam",
    "id": 1463491,
    "login": "bassam",
    "node_id": "MDQ6VXNlcjE0NjM0OTE=",
    "organizations_url": "https://api.github.com/users/bassam/orgs",
    "received_events_url": "https://api.github.com/users/bassam/received_events",
    "repos_url": "https://api.github.com/users/bassam/repos",
    "site_admin": false,
    "starred_url": "https://api.github.com/users/bassam/starred{/owner}{/repo}",
    "subscriptions_url": "https://api.github.com/users/bassam/subscriptions",
    "type": "User",
    "url": "https://api.github.com/users/bassam"
  },
  "milestone": null,
  "node_id": "MDExOlB1bGxSZXF1ZXN0MjczNzYxNjY0",
  "number": 3061,
  "patch_url": "https://github.com/rook/rook/pull/3061.patch",
  "rebaseable": null,
  "requested_reviewers": [
    {
      "avatar_url": "https://avatars2.githubusercontent.com/u/4313439?v=4",
      "events_url": "https://api.github.com/users/jbw976/events{/privacy}",
      "followers_url": "https://api.github.com/users/jbw976/followers",
      "following_url": "https://api.github.com/users/jbw976/following{/other_user}",
      "gists_url": "https://api.github.com/users/jbw976/gists{/gist_id}",
      "gravatar_id": "",
      "html_url": "https://github.com/jbw976",
      "id": 4313439,
      "login": "jbw976",
      "node_id": "MDQ6VXNlcjQzMTM0Mzk=",
      "organizations_url": "https://api.github.com/users/jbw976/orgs",
      "received_events_url": "https://api.github.com/users/jbw976/received_events",
      "repos_url": "https://api.github.com/users/jbw976/repos",
      "site_admin": false,
      "starred_url": "https://api.github.com/users/jbw976/starred{/owner}{/repo}",
      "subscriptions_url": "https://api.github.com/users/jbw976/subscriptions",
      "type": "User",
      "url": "https://api.github.com/users/jbw976"
    }
  ],
  "requested_teams": [],
  "review_comment_url": "https://api.github.com/repos/rook/rook/pulls/comments{/number}",
  "review_comments": 6,
  "review_comments_url": "https://api.github.com/repos/rook/rook/pulls/3061/comments",
  "state": "closed",
  "statuses_url": "https://api.github.com/repos/rook/rook/statuses/81f55a12eb8b7f2c8af74431f20861520bf2c8db",
  "title": "Promote builds to master and release rather than alpha, beta, and stable",
  "updated_at": "2019-09-16T21:49:59Z",
  "url": "https://api.github.com/repos/rook/rook/pulls/3061",
  "user": {
    "avatar_url": "https://avatars0.githubusercontent.com/u/1048514?v=4",
    "events_url": "https://api.github.com/users/travisn/events{/privacy}",
    "followers_url": "https://api.github.com/users/travisn/followers",
    "following_url": "https://api.github.com/users/travisn/following{/other_user}",
    "gists_url": "https://api.github.com/users/travisn/gists{/gist_id}",
    "gravatar_id": "",
    "html_url": "https://github.com/travisn",
    "id": 1048514,
    "login": "travisn",
    "node_id": "MDQ6VXNlcjEwNDg1MTQ=",
    "organizations_url": "https://api.github.com/users/travisn/orgs",
    "received_events_url": "https://api.github.com/users/travisn/received_events",
    "repos_url": "https://api.github.com/users/travisn/repos",
    "site_admin": false,
    "starred_url": "https://api.github.com/users/travisn/starred{/owner}{/repo}",
    "subscriptions_url": "https://api.github.com/users/travisn/subscriptions",
    "type": "User",
    "url": "https://api.github.com/users/travisn"
  }
}